Workbook

Sheet Leia-me
A1: Contrata + NATA — Planilha de Gestão do Cadastro de Fornecedores
A2: Instituto NATA · Versão 1.0 · Setembro/2026
A4: Para que serve | B4: Controlar o credenciamento (Cadastro e Habilitação), enquadrar cada demanda na faixa correta, apontar o próximo do rodízio, julgar cotações com empate ficto, preferência local e desempate por equidade, registrar contratações, sanções e o Banco de Preços, e calcular os indicadores de inclusão do relatório semestral.
A5: Legenda de cores | B5: Texto AZUL = célula de entrada (digite). Texto PRETO = fórmula (não altere). Texto VERDE = valor vindo de outra aba. Fundo AMARELO = parâmetro ou célula-chave a revisar.
A6: Ordem de uso | B6: 1) Revise a aba Parâmetros (limites das faixas do ano, margens e metas). 2) Cadastre cada fornecedor habilitado na aba Cadastro (uma linha por fornecedor; nas colunas de linhas de fornecimento use os códigos separados por ponto e vírgula, ex.: L01;L07). 3) Preencha o checklist na aba Habilitação. 4) Para cada demanda, registre a linha na aba Contratações — a faixa e o modo de seleção são calculados. 5) Na Faixa 1, use a aba Rodízio: informe a linha e o território e ela aponta o próximo credenciado. 6) Nas Faixas 2 e 3, use a aba Cotações para o mapa comparativo. 7) Alimente o Banco de Preços a cada contratação. 8) A aba Indicadores resume tudo para o relatório semestral.
A7: Linhas de exemplo | B7: As abas Cadastro, Habilitação, Contratações, Banco de Preços e Sanções trazem linhas de EXEMPLO (marcadas na coluna de observações) apenas para mostrar o formato esperado. Apague-as antes do uso real.
A8: Atualização anual | B8: Quando o Governo Federal publicar o decreto que atualiza os valores da Lei nº 14.133/2021 (em 2026: Decreto nº 12.807/2025), altere apenas as células amarelas da aba Parâmetros; todas as fórmulas se ajustam.
A9: Fonte dos limites | B9: Faixa 1 = art. 95, § 2º, da Lei nº 14.133/2021 (contrato verbal), R$ 13.098,41 em 2026; Faixa 2 = art. 75, II (dispensa para compras e serviços), R$ 65.492,11 em 2026 — Decreto nº 12.807/2025. Margens de 10% inspiradas nos arts. 44 e 48, § 3º, da LC nº 123/2006.
A10: Proteção de dados | B10: Esta planilha contém dados pessoais (CPF, contato, autodeclarações). Restrinja o acesso à Comissão, ao Financeiro e ao Controle Interno; não publique as colunas de raça/cor e CadÚnico; a lista pública deve conter apenas nome/razão social, CNPJ parcial, linhas, porte, indicação de negócio liderado por mulher (se autorizado), município e validade.

Sheet Parâmetros
A1: Parâmetros do Contrata + NATA
A2: Células amarelas: revise anualmente ou quando a Diretoria alterar a Política
A4: Parâmetro | B4: Valor | C4: Fonte / observação
A5: Ano de referência | B5: 2026 | C5: Ano do decreto federal de atualização
A6: Decreto federal de atualização | B6: Decreto nº 12.807/2025 | C6: Publicado em 29/12/2025; vigente a partir de 01/01/2026
A7: Limite superior da Faixa 1 (R$) | B7: 13098.41 | C7: Art. 95, § 2º, Lei nº 14.133/2021 — contrato verbal / contratação direta simplificada
A8: Limite superior da Faixa 2 (R$) | B8: 65492.11 | C8: Art. 75, II, Lei nº 14.133/2021 — dispensa para compras e serviços
A9: Margem do empate ficto (pequenos negócios) | B9: 0.1 | C9: Inspirada no art. 44, § 1º, LC nº 123/2006
A10: Margem de preferência local/regional | B10: 0.1 | C10: Inspirada no art. 48, § 3º, LC nº 123/2006 e art. 18 da IN SEGES/MGI nº 52/2025
A11: Teto sobre a média do Banco de Preços (Faixa 1) | B11: 0.1 | C11: Proposta no rodízio aceita até média + esta margem
A12: Validade do credenciamento (meses) | B12: 24 | C12: Art. 22 da Política
A13: Antecedência do alerta de certidões (dias) | B13: 15 | C13: Aviso "RENOVAR" antes do vencimento
A14: Meta: % do valor com pequenos negócios | B14: 0.7 | C14: Art. 15 da Política
A15: Meta: % do valor com negócios liderados por mulheres | B15: 0.3 | C15: Art. 15 da Política
A16: Meta: % do valor com fornecedores T1 | B16: 0.5 | C16: Art. 15 da Política
A17: Meta: avaliação média mínima | B17: 4 | C17: Manual, item 7
A18: Meta: % máximo de contratações de urgência | B18: 0.05 | C18: Manual, item 7
A19: Mínimo de propostas válidas na Faixa 2 | B19: 3 | C19: Item 7.1 do Edital
A22: Listas de validação
A23: Portes | B23: Pequeno negócio (auto) | C23: Territórios | D23: Status | E23: Faixas | F23: Modos | G23: Sim/Não | H23: Linhas | I23: Nome da linha
A24: MEI | B24: MEI | C24: T1 | D24: Ativo | E24: Faixa 1 | F24: Rodízio | G24: S | H24: L01 | I24: Alimentação — lanches e kits
A25: ME | B25: ME | C25: T2 | D25: Em análise | E25: Faixa 2 | F25: Sorteio | G25: N | H25: L02 | I25: Bufê e churrasqueiro
A26: EPP | B26: EPP | C26: T3 | D26: Inativo temporário | E26: Faixa 3 | F26: Cotação | H26: L03 | I26: Sonorização e música
A27: Cooperativa | B27: Cooperativa | D27: Suspenso | F27: Chamada | H27: L04 | I27: Estruturas para eventos
A28: PF autônoma | B28: PF autônoma | D28: Descredenciado | F28: Urgência | H28: L05 | I28: Locação de mobiliário e equipamentos
A29: Médio/Grande | H29: L06 | I29: Cerimonial e apoio a eventos
H30: L07 | I30: Recreação, oficinas e atrações
H31: L08 | I31: Atividade física e bem-estar
H32: L09 | I32: Fotografia e audiovisual
H33: L10 | I33: Comunicação visual e impressão
H34: L11 | I34: Confecção e uniformes
H35: L12 | I35: Artesanato e economia criativa
H36: L13 | I36: Materiais pedagógicos e de consumo
H37: L14 | I37: Transporte
H38: L15 | I38: Manutenção e pequenos reparos
H39: L16 | I39: Limpeza e resíduos
H40: L17 | I40: Saúde e segurança em eventos
H41: L18 | I41: Tecnologia da informação
... H43: L20 | I43: Beleza e caracterização

Sheet Cadastro
A1: Cadastro de Fornecedores Credenciados
A2: Uma linha por fornecedor. Colunas azuis: digite. Colunas pretas: calculadas. Linhas de fornecimento: códigos separados por ";" (ex.: L01;L07).
A4: ID | B4: Razão social / Nome | C4: CNPJ / CPF | D4: Porte | E4: Pequeno negócio? | F4: Liderado por mulher? | G4: Mulher negra ou CadÚnico? (facultativo) | H4: Município da sede | I4: Território | J4: Linhas de fornecimento | K4: Telefone / WhatsApp | L4: E-mail | M4: Data do credenciamento | N4: Validade | O4: Status | P4: Venc. certidão federal | Q4: Venc. FGTS | R4: Venc. CNDT | S4: Venc. municipal | T4: Alerta certidões | U4: Nº contratações | V4: Valor contratado (R$) | W4: Avaliação média | X4: Última contratação | Y4: Observações
A5: F001 | B5: Maria das Dores Lanches ME | C5: 12.345.678/0001-90 | D5: ME | E5: =IF(D5="","",IF(OR(D5="MEI",D5="ME",D5="EPP",D5="Cooperativa",D5="PF autônoma"),"S","N")) -> S | F5: S | G5: S | H5: Mesquita | I5: T1 | J5: L01;L02 | K5: (21) 99999-0001 | L5: maria@exemplo.com | M5: 46296 | N5: =IF(M5="","",EDATE(M5,Parâmetros!$B$12)) -> 47027 | O5: Ativo | P5: 46476 | Q5: 46341 | R5: 46476 | S5: 46418 | T5: =IF(A5="","",IF(OR(AND(P5<>"",P5<=TODAY()+Parâmetros!$B$13),AND(Q5<>"",Q5<=TODAY()+Parâmetros!$B$13),AND(R5<>"",R5<=TODAY()+Parâmetros!$B$13),AND(S5<>"",S5<=TODAY()+Parâmetros!$B$13)),"RENOVAR","OK")) -> OK | U5: =IF(A5="","",COUNTIF(Contratações!$I$5:$I$504,A5)) -> 1 | V5: =IF(A5="","",SUMIF(Contratações!$I$5:$I$504,A5,Contratações!$N$5:$N$504)) -> 3850 | W5: =IF(A5="","",IFERROR(AVERAGEIFS(Contratações!$R$5:$R$504,Contratações!$I$5:$I$504,A5,Contratações!$R$5:$R$504,">0"),"")) -> 5 | X5: =IF(A5="","",IF(U5=0,"nunca",_xlfn.MAXIFS(Contratações!$O$5:$O$504,Contratações!$I$5:$I$504,A5))) -> 46315 | Y5: EXEMPLO — apagar
A6: F002 | B6: João Som & Luz MEI | C6: 23.456.789/0001-01 | D6: MEI | E6: =IF(D6="","",IF(OR(D6="MEI",D6="ME",D6="EPP",D6="Cooperativa",D6="PF autônoma"),"S","N")) -> S | F6: N | G6: N | H6: Nova Iguaçu | I6: T2 | J6: L03;L04 | K6: (21) 99999-0002 | L6: joao@exemplo.com | M6: 46298 | N6: =IF(M6="","",EDATE(M6,Parâmetros!$B$12)) -> 47029 | O6: Ativo | P6: 46476 | Q6: 46315 | R6: 46476 | S6: 46446 | T6: =IF(A6="","",IF(OR(AND(P6<>"",P6<=TODAY()+Parâmetros!$B$13),AND(Q6<>"",Q6<=TODAY()+Parâmetros!$B$13),AND(R6<>"",R6<=TODAY()+Parâmetros!$B$13),AND(S6<>"",S6<=TODAY()+Parâmetros!$B$13)),"RENOVAR","OK")) -> OK | U6: =IF(A6="","",COUNTIF(Contratações!$I$5:$I$504,A6)) -> 1 | V6: =IF(A6="","",SUMIF(Contratações!$I$5:$I$504,A6,Contratações!$N$5:$N$504)) -> 17200 | W6: =IF(A6="","",IFERROR(AVERAGEIFS(Contratações!$R$5:$R$504,Contratações!$I$5:$I$504,A6,Contratações!$R$5:$R$504,">0"),"")) -> 4 | X6: =IF(A6="","",IF(U6=0,"nunca",_xlfn.MAXIFS(Contratações!$O$5:$O$504,Contratações!$I$5:$I$504,A6))) -> 46318 | Y6: EXEMPLO — apagar
A7: F003 | B7: Coletivo Mãos de Mesquita (cooperativa) | C7: 34.567.890/0001-12 | D7: Cooperativa | E7: =IF(D7="","",IF(OR(D7="MEI",D7="ME",D7="EPP",D7="Cooperativa",D7="PF autônoma"),"S","N")) -> S | F7: S | G7: S | H7: Mesquita | I7: T1 | J7: L12;L11 | K7: (21) 99999-0003 | L7: coletivo@exemplo.com | M7: 46300 | N7: =IF(M7="","",EDATE(M7,Parâmetros!$B$12)) -> 47031 | O7: Ativo | P7: 46476 | Q7: 46476 | R7: 46476 | S7: 46476 | T7: =IF(A7="","",IF(OR(AND(P7<>"",P7<=TODAY()+Parâmetros!$B$13),AND(Q7<>"",Q7<=TODAY()+Parâmetros!$B$13),AND(R7<>"",R7<=TODAY()+Parâmetros!$B$13),AND(S7<>"",S7<=TODAY()+Parâmetros!$B$13)),"RENOVAR","OK")) -> OK | U7: =IF(A7="","",COUNTIF(Contratações!$I$5:$I$504,A7)) -> 1 | V7: =IF(A7="","",SUMIF(Contratações!$I$5:$I$504,A7,Contratações!$N$5:$N$504)) -> 9600 | W7: =IF(A7="","",IFERROR(AVERAGEIFS(Contratações!$R$5:$R$504,Contratações!$I$5:$I$504,A7,Contratações!$R$5:$R$504,">0"),"")) -> 5 | X7: =IF(A7="","",IF(U7=0,"nunca",_xlfn.MAXIFS(Contratações!$O$5:$O$504,Contratações!$I$5:$I$504,A7))) -> 46317 | Y7: EXEMPLO — apagar
A8: F004 | B8: Ana Paula Silva (oficineira) | C8: 123.456.789-00 | D8: PF autônoma | E8: =IF(D8="","",IF(OR(D8="MEI",D8="ME",D8="EPP",D8="Cooperativa",D8="PF autônoma"),"S","N")) -> S | F8: S | G8: N | H8: Rio de Janeiro | I8: T1 | J8: L07;L08 | K8: (21) 99999-0004 | L8: ana@exemplo.com | M8: 46303 | N8: =IF(M8="","",EDATE(M8,Parâmetros!$B$12)) -> 47034 | O8: Ativo | P8: 46476 | R8: 46476 | T8: =IF(A8="","",IF(OR(AND(P8<>"",P8<=TODAY()+Parâmetros!$B$13),AND(Q8<>"",Q8<=TODAY()+Parâmetros!$B$13),AND(R8<>"",R8<=TODAY()+Parâmetros!$B$13),AND(S8<>"",S8<=TODAY()+Parâmetros!$B$13)),"RENOVAR","OK")) -> OK | U8: =IF(A8="","",COUNTIF(Contratações!$I$5:$I$504,A8)) -> 1 | V8: =IF(A8="","",SUMIF(Contratações!$I$5:$I$504,A8,Contratações!$N$5:$N$504)) -> 4000 | W8: =IF(A8="","",IFERROR(AVERAGEIFS(Contratações!$R$5:$R$504,Contratações!$I$5:$I$504,A8,Contratações!$R$5:$R$504,">0"),"")) -> 5 | X8: =IF(A8="","",IF(U8=0,"nunca",_xlfn.MAXIFS(Contratações!$O$5:$O$504,Contratações!$I$5:$I$504,A8))) -> 46331 | Y8: EXEMPLO — apagar
A9: F005 | B9: Gráfica Baixada EPP | C9: 45.678.901/0001-23 | D9: EPP | E9: =IF(D9="","",IF(OR(D9="MEI",D9="ME",D9="EPP",D9="Cooperativa",D9="PF autônoma"),"S","N")) -> S | F9: N | G9: N | H9: Duque de Caxias | I9: T2 | J9: L10 | K9: (21) 99999-0005 | L9: grafica@exemplo.com | M9: 46305 | N9: =IF(M9="","",EDATE(M9,Parâmetros!$B$12)) -> 47036 | O9: Ativo | P9: 46476 | Q9: 46357 | R9: 46476 | S9: 46476 | T9: =IF(A9="","",IF(OR(AND(P9<>"",P9<=TODAY()+Parâmetros!$B$13),AND(Q9<>"",Q9<=TODAY()+Parâmetros!$B$13),AND(R9<>"",R9<=TODAY()+Parâmetros!$B$13),AND(S9<>"",S9<=TODAY()+Parâmetros!$B$13)),"RENOVAR","OK")) -> OK | U9: =IF(A9="","",COUNTIF(Contratações!$I$5:$I$504,A9)) -> 1 | V9: =IF(A9="","",SUMIF(Contratações!$I$5:$I$504,A9,Contratações!$N$5:$N$504)) -> 5900 | W9: =IF(A9="","",IFERROR(AVERAGEIFS(Contratações!$R$5:$R$504,Contratações!$I$5:$I$504,A9,Contratações!$R$5:$R$504,">0"),"")) -> 3 | X9: =IF(A9="","",IF(U9=0,"nunca",_xlfn.MAXIFS(Contratações!$O$5:$O$504,Contratações!$I$5:$I$504,A9))) -> 46332 | Y9: EXEMPLO — apagar
A10: F006 | B10: Lanches da Tia Rosa MEI | C10: 56.789.012/0001-34 | D10: MEI | E10: =IF(D10="","",IF(OR(D10="MEI",D10="ME",D10="EPP",D10="Cooperativa",D10="PF autônoma"),"S","N")) -> S | F10: S | G10: S | H10: Mesquita | I10: T1 | J10: L01 | K10: (21) 99999-0006 | L10: rosa@exemplo.com | M10: 46307 | N10: =IF(M10="","",EDATE(M10,Parâmetros!$B$12)) -> 47038 | O10: Inativo temporário | P10: 46295 | Q10: 46357 | R10: 46476 | S10: 46476 | T10: =IF(A10="","",IF(OR(AND(P10<>"",P10<=TODAY()+Parâmetros!$B$13),AND(Q10<>"",Q10<=TODAY()+Parâmetros!$B$13),AND(R10<>"",R10<=TODAY()+Parâmetros!$B$13),AND(S10<>"",S10<=TODAY()+Parâmetros!$B$13)),"RENOVAR","OK")) -> OK | U10: =IF(A10="","",COUNTIF(Contratações!$I$5:$I$504,A10)) -> 0 | V10: =IF(A10="","",SUMIF(Contratações!$I$5:$I$504,A10,Contratações!$N$5:$N$504)) -> 0 | W10: =IF(A10="","",IFERROR(AVERAGEIFS(Contratações!$R$5:$R$504,Contratações!$I$5:$I$504,A10,Contratações!$R$5:$R$504,">0"),"")) | X10: =IF(A10="","",IF(U10=0,"nunca",_xlfn.MAXIFS(Contratações!$O$5:$O$504,Contratações!$I$5:$I$504,A10))) -> nunca | Y10: EXEMPLO — apagar (certidão federal vencida)
E11: =IF(D11="","",IF(OR(D11="MEI",D11="ME",D11="EPP",D11="Cooperativa",D11="PF autônoma"),"S","N")) | N11: =IF(M11="","",EDATE(M11,Parâmetros!$B$12)) | T11: =IF(A11="","",IF(OR(AND(P11<>"",P11<=TODAY()+Parâmetros!$B$13),AND(Q11<>"",Q11<=TODAY()+Parâmetros!$B$13),AND(R11<>"",R11<=TODAY()+Parâmetros!$B$13),AND(S11<>"",S11<=TODAY()+Parâmetros!$B$13)),"RENOVAR","OK")) | U11: =IF(A11="","",COUNTIF(Contratações!$I$5:$I$504,A11)) | V11: =IF(A11="","",SUMIF(Contratações!$I$5:$I$504,A11,Contratações!$N$5:$N$504)) | W11: =IF(A11="","",IFERROR(AVERAGEIFS(Contratações!$R$5:$R$504,Contratações!$I$5:$I$504,A11,Contratações!$R$5:$R$504,">0"),"")) | X11: =IF(A11="","",IF(U11=0,"nunca",_xlfn.MAXIFS(Contratações!$O$5:$O$504,Contratações!$I$5:$I$504,A11)))
E12: =IF(D12="","",IF(OR(D12="MEI",D12="ME",D12="EPP",D12="Cooperativa",D12="PF autônoma"),"S","N")) | N12: =IF(M12="","",EDATE(M12,Parâmetros!$B$12)) | T12: =IF(A12="","",IF(OR(AND(P12<>"",P12<=TODAY()+Parâmetros!$B$13),AND(Q12<>"",Q12<=TODAY()+Parâmetros!$B$13),AND(R12<>"",R12<=TODAY()+Parâmetros!$B$13),AND(S12<>"",S12<=TODAY()+Parâmetros!$B$13)),"RENOVAR","OK")) | U12: =IF(A12="","",COUNTIF(Contratações!$I$5:$I$504,A12)) | V12: =IF(A12="","",SUMIF(Contratações!$I$5:$I$504,A12,Contratações!$N$5:$N$504)) | W12: =IF(A12="","",IFERROR(AVERAGEIFS(Contratações!$R$5:$R$504,Contratações!$I$5:$I$504,A12,Contratações!$R$5:$R$504,">0"),"")) | X12: =IF(A12="","",IF(U12=0,"nunca",_xlfn.MAXIFS(Contratações!$O$5:$O$504,Contratações!$I$5:$I$504,A12)))
E13: =IF(D13="","",IF(OR(D13="MEI",D13="ME",D13="EPP",D13="Cooperativa",D13="PF autônoma"),"S","N")) | N13: =IF(M13="","",EDATE(M13,Parâmetros!$B$12)) | T13: =IF(A13="","",IF(OR(AND(P13<>"",P13<=TODAY()+Parâmetros!$B$13),AND(Q13<>"",Q13<=TODAY()+Parâmetros!$B$13),AND(R13<>"",R13<=TODAY()+Parâmetros!$B$13),AND(S13<>"",S13<=TODAY()+Parâmetros!$B$13)),"RENOVAR","OK")) | U13: =IF(A13="","",COUNTIF(Contratações!$I$5:$I$504,A13)) | V13: =IF(A13="","",SUMIF(Contratações!$I$5:$I$504,A13,Contratações!$N$5:$N$504)) | W13: =IF(A13="","",IFERROR(AVERAGEIFS(Contratações!$R$5:$R$504,Contratações!$I$5:$I$504,A13,Contratações!$R$5:$R$504,">0"),"")) | X13: =IF(A13="","",IF(U13=0,"nunca",_xlfn.MAXIFS(Contratações!$O$5:$O$504,Contratações!$I$5:$I$504,A13)))
E14: =IF(D14="","",IF(OR(D14="MEI",D14="ME",D14="EPP",D14="Cooperativa",D14="PF autônoma"),"S","N")) | N14: =IF(M14="","",EDATE(M14,Parâmetros!$B$12)) | T14: =IF(A14="","",IF(OR(AND(P14<>"",P14<=TODAY()+Parâmetros!$B$13),AND(Q14<>"",Q14<=TODAY()+Parâmetros!$B$13),AND(R14<>"",R14<=TODAY()+Parâmetros!$B$13),AND(S14<>"",S14<=TODAY()+Parâmetros!$B$13)),"RENOVAR","OK")) | U14: =IF(A14="","",COUNTIF(Contratações!$I$5:$I$504,A14)) | V14: =IF(A14="","",SUMIF(Contratações!$I$5:$I$504,A14,Contratações!$N$5:$N$504)) | W14: =IF(A14="","",IFERROR(AVERAGEIFS(Contratações!$R$5:$R$504,Contratações!$I$5:$I$504,A14,Contratações!$R$5:$R$504,">0"),"")) | X14: =IF(A14="","",IF(U14=0,"nunca",_xlfn.MAXIFS(Contratações!$O$5:$O$504,Contratações!$I$5:$I$504,A14)))
E15: =IF(D15="","",IF(OR(D15="MEI",D15="ME",D15="EPP",D15="Cooperativa",D15="PF autônoma"),"S","N")) | N15: =IF(M15="","",EDATE(M15,Parâmetros!$B$12)) | T15: =IF(A15="","",IF(OR(AND(P15<>"",P15<=TODAY()+Parâmetros!$B$13),AND(Q15<>"",Q15<=TODAY()+Parâmetros!$B$13),AND(R15<>"",R15<=TODAY()+Parâmetros!$B$13),AND(S15<>"",S15<=TODAY()+Parâmetros!$B$13)),"RENOVAR","OK")) | U15: =IF(A15="","",COUNTIF(Contratações!$I$5:$I$504,A15)) | V15: =IF(A15="","",SUMIF(Contratações!$I$5:$I$504,A15,Contratações!$N$5:$N$504)) | W15: =IF(A15="","",IFERROR(AVERAGEIFS(Contratações!$R$5:$R$504,Contratações!$I$5:$I$504,A15,Contratações!$R$5:$R$504,">0"),"")) | X15: =IF(A15="","",IF(U15=0,"nunca",_xlfn.MAXIFS(Contratações!$O$5:$O$504,Contratações!$I$5:$I$504,A15)))
E16: =IF(D16="","",IF(OR(D16="MEI",D16="ME",D16="EPP",D16="Cooperativa",D16="PF autônoma"),"S","N")) | N16: =IF(M16="","",EDATE(M16,Parâmetros!$B$12)) | T16: =IF(A16="","",IF(OR(AND(P16<>"",P16<=TODAY()+Parâmetros!$B$13),AND(Q16<>"",Q16<=TODAY()+Parâmetros!$B$13),AND(R16<>"",R16<=TODAY()+Parâmetros!$B$13),AND(S16<>"",S16<=TODAY()+Parâmetros!$B$13)),"RENOVAR","OK")) | U16: =IF(A16="","",COUNTIF(Contratações!$I$5:$I$504,A16)) | V16: =IF(A16="","",SUMIF(Contratações!$I$5:$I$504,A16,Contratações!$N$5:$N$504)) | W16: =IF(A16="","",IFERROR(AVERAGEIFS(Contratações!$R$5:$R$504,Contratações!$I$5:$I$504,A16,Contratações!$R$5:$R$504,">0"),"")) | X16: =IF(A16="","",IF(U16=0,"nunca",_xlfn.MAXIFS(Contratações!$O$5:$O$504,Contratações!$I$5:$I$504,A16)))
E17: =IF(D17="","",IF(OR(D17="MEI",D17="ME",D17="EPP",D17="Cooperativa",D17="PF autônoma"),"S","N")) | N17: =IF(M17="","",EDATE(M17,Parâmetros!$B$12)) | T17: =IF(A17="","",IF(OR(AND(P17<>"",P17<=TODAY()+Parâmetros!$B$13),AND(Q17<>"",Q17<=TODAY()+Parâmetros!$B$13),AND(R17<>"",R17<=TODAY()+Parâmetros!$B$13),AND(S17<>"",S17<=TODAY()+Parâmetros!$B$13)),"RENOVAR","OK")) | U17: =IF(A17="","",COUNTIF(Contratações!$I$5:$I$504,A17)) | V17: =IF(A17="","",SUMIF(Contratações!$I$5:$I$504,A17,Contratações!$N$5:$N$504)) | W17: =IF(A17="","",IFERROR(AVERAGEIFS(Contratações!$R$5:$R$504,Contratações!$I$5:$I$504,A17,Contratações!$R$5:$R$504,">0"),"")) | X17: =IF(A17="","",IF(U17=0,"nunca",_xlfn.MAXIFS(Contratações!$O$5:$O$504,Contratações!$I$5:$I$504,A17)))
E18: =IF(D18="","",IF(OR(D18="MEI",D18="ME",D18="EPP",D18="Cooperativa",D18="PF autônoma"),"S","N")) | N18: =IF(M18="","",EDATE(M18,Parâmetros!$B$12)) | T18: =IF(A18="","",IF(OR(AND(P18<>"",P18<=TODAY()+Parâmetros!$B$13),AND(Q18<>"",Q18<=TODAY()+Parâmetros!$B$13),AND(R18<>"",R18<=TODAY()+Parâmetros!$B$13),AND(S18<>"",S18<=TODAY()+Parâmetros!$B$13)),"RENOVAR","OK")) | U18: =IF(A18="","",COUNTIF(Contratações!$I$5:$I$504,A18)) | V18: =IF(A18="","",SUMIF(Contratações!$I$5:$I$504,A18,Contratações!$N$5:$N$504)) | W18: =IF(A18="","",IFERROR(AVERAGEIFS(Contratações!$R$5:$R$504,Contratações!$I$5:$I$504,A18,Contratações!$R$5:$R$504,">0"),"")) | X18: =IF(A18="","",IF(U18=0,"nunca",_xlfn.MAXIFS(Contratações!$O$5:$O$504,Contratações!$I$5:$I$504,A18)))
E19: =IF(D19="","",IF(OR(D19="MEI",D19="ME",D19="EPP",D19="Cooperativa",D19="PF autônoma"),"S","N")) | N19: =IF(M19="","",EDATE(M19,Parâmetros!$B$12)) | T19: =IF(A19="","",IF(OR(AND(P19<>"",P19<=TODAY()+Parâmetros!$B$13),AND(Q19<>"",Q19<=TODAY()+Parâmetros!$B$13),AND(R19<>"",R19<=TODAY()+Parâmetros!$B$13),AND(S19<>"",S19<=TODAY()+Parâmetros!$B$13)),"RENOVAR","OK")) | U19: =IF(A19="","",COUNTIF(Contratações!$I$5:$I$504,A19)) | V19: =IF(A19="","",SUMIF(Contratações!$I$5:$I$504,A19,Contratações!$N$5:$N$504)) | W19: =IF(A19="","",IFERROR(AVERAGEIFS(Contratações!$R$5:$R$504,Contratações!$I$5:$I$504,A19,Contratações!$R$5:$R$504,">0"),"")) | X19: =IF(A19="","",IF(U19=0,"nunca",_xlfn.MAXIFS(Contratações!$O$5:$O$504,Contratações!$I$5:$I$504,A19)))
E20: =IF(D20="","",IF(OR(D20="MEI",D20="ME",D20="EPP",D20="Cooperativa",D20="PF autônoma"),"S","N")) | N20: =IF(M20="","",EDATE(M20,Parâmetros!$B$12)) | T20: =IF(A20="","",IF(OR(AND(P20<>"",P20<=TODAY()+Parâmetros!$B$13),AND(Q20<>"",Q20<=TODAY()+Parâmetros!$B$13),AND(R20<>"",R20<=TODAY()+Parâmetros!$B$13),AND(S20<>"",S20<=TODAY()+Parâmetros!$B$13)),"RENOVAR","OK")) | U20: =IF(A20="","",COUNTIF(Contratações!$I$5:$I$504,A20)) | V20: =IF(A20="","",SUMIF(Contratações!$I$5:$I$504,A20,Contratações!$N$5:$N$504)) | W20: =IF(A20="","",IFERROR(AVERAGEIFS(Contratações!$R$5:$R$504,Contratações!$I$5:$I$504,A20,Contratações!$R$5:$R$504,">0"),"")) | X20: =IF(A20="","",IF(U20=0,"nunca",_xlfn.MAXIFS(Contratações!$O$5:$O$504,Contratações!$I$5:$I$504,A20)))
E21: =IF(D21="","",IF(OR(D21="MEI",D21="ME",D21="EPP",D21="Cooperativa",D21="PF autônoma"),"S","N")) | N21: =IF(M21="","",EDATE(M21,Parâmetros!$B$12)) | T21: =IF(A21="","",IF(OR(AND(P21<>"",P21<=TODAY()+Parâmetros!$B$13),AND(Q21<>"",Q21<=TODAY()+Parâmetros!$B$13),AND(R21<>"",R21<=TODAY()+Parâmetros!$B$13),AND(S21<>"",S21<=TODAY()+Parâmetros!$B$13)),"RENOVAR","OK")) | U21: =IF(A21="","",COUNTIF(Contratações!$I$5:$I$504,A21)) | V21: =IF(A21="","",SUMIF(Contratações!$I$5:$I$504,A21,Contratações!$N$5:$N$504)) | W21: =IF(A21="","",IFERROR(AVERAGEIFS(Contratações!$R$5:$R$504,Contratações!$I$5:$I$504,A21,Contratações!$R$5:$R$504,">0"),"")) | X21: =IF(A21="","",IF(U21=0,"nunca",_xlfn.MAXIFS(Contratações!$O$5:$O$504,Contratações!$I$5:$I$504,A21)))
E22: =IF(D22="","",IF(OR(D22="MEI",D22="ME",D22="EPP",D22="Cooperativa",D22="PF autônoma"),"S","N")) | N22: =IF(M22="","",EDATE(M22,Parâmetros!$B$12)) | T22: =IF(A22="","",IF(OR(AND(P22<>"",P22<=TODAY()+Parâmetros!$B$13),AND(Q22<>"",Q22<=TODAY()+Parâmetros!$B$13),AND(R22<>"",R22<=TODAY()+Parâmetros!$B$13),AND(S22<>"",S22<=TODAY()+Parâmetros!$B$13)),"RENOVAR","OK")) | U22: =IF(A22="","",COUNTIF(Contratações!$I$5:$I$504,A22)) | V22: =IF(A22="","",SUMIF(Contratações!$I$5:$I$504,A22,Contratações!$N$5:$N$504)) | W22: =IF(A22="","",IFERROR(AVERAGEIFS(Contratações!$R$5:$R$504,Contratações!$I$5:$I$504,A22,Contratações!$R$5:$R$504,">0"),"")) | X22: =IF(A22="","",IF(U22=0,"nunca",_xlfn.MAXIFS(Contratações!$O$5:$O$504,Contratações!$I$5:$I$504,A22)))
... E304: =IF(D304="","",IF(OR(D304="MEI",D304="ME",D304="EPP",D304="Cooperativa",D304="PF autônoma"),"S","N")) | N304: =IF(M304="","",EDATE(M304,Parâmetros!$B$12)) | T304: =IF(A304="","",IF(OR(AND(P304<>"",P304<=TODAY()+Parâmetros!$B$13),AND(Q304<>"",Q304<=TODAY()+Parâmetros!$B$13),AND(R304<>"",R304<=TODAY()+Parâmetros!$B$13),AND(S304<>"",S304<=TODAY()+Parâmetros!$B$13)),"RENOVAR","OK")) | U304: =IF(A304="","",COUNTIF(Contratações!$I$5:$I$504,A304)) | V304: =IF(A304="","",SUMIF(Contratações!$I$5:$I$504,A304,Contratações!$N$5:$N$504)) | W304: =IF(A304="","",IFERROR(AVERAGEIFS(Contratações!$R$5:$R$504,Contratações!$I$5:$I$504,A304,Contratações!$R$5:$R$504,">0"),"")) | X304: =IF(A304="","",IF(U304=0,"nunca",_xlfn.MAXIFS(Contratações!$O$5:$O$504,Contratações!$I$5:$I$504,A304)))

Sheet Habilitação
A1: Checklist de Habilitação
A2: Marque S (apresentado e válido), N (pendente) ou NA (não se aplica ao tipo). Status calculado: Completo / Pendente.
A4: ID | B4: Fornecedor | C4: CCMEI / contrato social / estatuto | D4: Ata de eleição (coop.) | E4: CNPJ | F4: Declaração ME/EPP | G4: Identidade e CPF | H4: Comprovante de endereço | I4: Certidão RFB/PGFN | J4: CRF/FGTS | K4: CNDT | L4: Certidão municipal | M4: Alvará / licença | N4: NIT/PIS (PF) | O4: Portfólio / atestados | P4: Comprovante bancário | Q4: Anexo II Requerimento | R4: Anexo III Declaração Unificada | S4: Anexo IV Mulher (opcional) | T4: Anexo V Termo de Adesão | U4: Consulta CEIS/CNEP/CEPIM (data) | V4: Pendências (nº de N) | W4: Status | X4: Data da análise | Y4: Analista | Z4: Observações
A5: F001 | B5: =IF(A5="","",IFERROR(INDEX(Cadastro!$B$5:$B$304,MATCH(A5,Cadastro!$A$5:$A$304,0)),"ID não encontrado")) -> Maria das Dores Lanches ME | C5: S | D5: NA | E5: S | F5: S | G5: S | H5: S | I5: S | J5: S | K5: S | L5: S | M5: S | N5: NA | O5: S | P5: S | Q5: S | R5: S | S5: S | T5: S | U5: S | V5: =IF(A5="","",COUNTIF(C5:U5,"N")) -> 0 | W5: =IF(A5="","",IF(V5=0,"Completo","Pendente")) -> Completo | Z5: EXEMPLO — apagar
A6: F002 | B6: =IF(A6="","",IFERROR(INDEX(Cadastro!$B$5:$B$304,MATCH(A6,Cadastro!$A$5:$A$304,0)),"ID não encontrado")) -> João Som & Luz MEI | C6: S | D6: NA | E6: S | F6: NA | G6: S | H6: S | I6: S | J6: S | K6: S | L6: N | M6: NA | N6: NA | O6: S | P6: S | Q6: S | R6: S | S6: NA | T6: S | U6: S | V6: =IF(A6="","",COUNTIF(C6:U6,"N")) -> 1 | W6: =IF(A6="","",IF(V6=0,"Completo","Pendente")) -> Pendente | Z6: EXEMPLO — apagar
B7: =IF(A7="","",IFERROR(INDEX(Cadastro!$B$5:$B$304,MATCH(A7,Cadastro!$A$5:$A$304,0)),"ID não encontrado")) | V7: =IF(A7="","",COUNTIF(C7:U7,"N")) | W7: =IF(A7="","",IF(V7=0,"Completo","Pendente"))
B8: =IF(A8="","",IFERROR(INDEX(Cadastro!$B$5:$B$304,MATCH(A8,Cadastro!$A$5:$A$304,0)),"ID não encontrado")) | V8: =IF(A8="","",COUNTIF(C8:U8,"N")) | W8: =IF(A8="","",IF(V8=0,"Completo","Pendente"))
B9: =IF(A9="","",IFERROR(INDEX(Cadastro!$B$5:$B$304,MATCH(A9,Cadastro!$A$5:$A$304,0)),"ID não encontrado")) | V9: =IF(A9="","",COUNTIF(C9:U9,"N")) | W9: =IF(A9="","",IF(V9=0,"Completo","Pendente"))
B10: =IF(A10="","",IFERROR(INDEX(Cadastro!$B$5:$B$304,MATCH(A10,Cadastro!$A$5:$A$304,0)),"ID não encontrado")) | V10: =IF(A10="","",COUNTIF(C10:U10,"N")) | W10: =IF(A10="","",IF(V10=0,"Completo","Pendente"))
B11: =IF(A11="","",IFERROR(INDEX(Cadastro!$B$5:$B$304,MATCH(A11,Cadastro!$A$5:$A$304,0)),"ID não encontrado")) | V11: =IF(A11="","",COUNTIF(C11:U11,"N")) | W11: =IF(A11="","",IF(V11=0,"Completo","Pendente"))
B12: =IF(A12="","",IFERROR(INDEX(Cadastro!$B$5:$B$304,MATCH(A12,Cadastro!$A$5:$A$304,0)),"ID não encontrado")) | V12: =IF(A12="","",COUNTIF(C12:U12,"N")) | W12: =IF(A12="","",IF(V12=0,"Completo","Pendente"))
B13: =IF(A13="","",IFERROR(INDEX(Cadastro!$B$5:$B$304,MATCH(A13,Cadastro!$A$5:$A$304,0)),"ID não encontrado")) | V13: =IF(A13="","",COUNTIF(C13:U13,"N")) | W13: =IF(A13="","",IF(V13=0,"Completo","Pendente"))
B14: =IF(A14="","",IFERROR(INDEX(Cadastro!$B$5:$B$304,MATCH(A14,Cadastro!$A$5:$A$304,0)),"ID não encontrado")) | V14: =IF(A14="","",COUNTIF(C14:U14,"N")) | W14: =IF(A14="","",IF(V14=0,"Completo","Pendente"))
B15: =IF(A15="","",IFERROR(INDEX(Cadastro!$B$5:$B$304,MATCH(A15,Cadastro!$A$5:$A$304,0)),"ID não encontrado")) | V15: =IF(A15="","",COUNTIF(C15:U15,"N")) | W15: =IF(A15="","",IF(V15=0,"Completo","Pendente"))
B16: =IF(A16="","",IFERROR(INDEX(Cadastro!$B$5:$B$304,MATCH(A16,Cadastro!$A$5:$A$304,0)),"ID não encontrado")) | V16: =IF(A16="","",COUNTIF(C16:U16,"N")) | W16: =IF(A16="","",IF(V16=0,"Completo","Pendente"))
B17: =IF(A17="","",IFERROR(INDEX(Cadastro!$B$5:$B$304,MATCH(A17,Cadastro!$A$5:$A$304,0)),"ID não encontrado")) | V17: =IF(A17="","",COUNTIF(C17:U17,"N")) | W17: =IF(A17="","",IF(V17=0,"Completo","Pendente"))
B18: =IF(A18="","",IFERROR(INDEX(Cadastro!$B$5:$B$304,MATCH(A18,Cadastro!$A$5:$A$304,0)),"ID não encontrado")) | V18: =IF(A18="","",COUNTIF(C18:U18,"N")) | W18: =IF(A18="","",IF(V18=0,"Completo","Pendente"))
... B304: =IF(A304="","",IFERROR(INDEX(Cadastro!$B$5:$B$304,MATCH(A304,Cadastro!$A$5:$A$304,0)),"ID não encontrado")) | V304: =IF(A304="","",COUNTIF(C304:U304,"N")) | W304: =IF(A304="","",IF(V304=0,"Completo","Pendente"))

Sheet Contratações
A1: Registro de Contratações (um dossiê por linha)
A2: Faixa e modo sugerido são calculados a partir do valor estimado e dos Parâmetros. Porte, gênero de liderança e território vêm do Cadastro.
A4: Nº dossiê | B4: Data do DFD | C4: Projeto / parceria | D4: Linha | E4: Descrição do objeto | F4: Valor estimado (R$) | G4: Faixa | H4: Modo sugerido | I4: ID fornecedor | J4: Fornecedor | K4: Pequeno negócio? | L4: Liderado por mulher? | M4: Território | N4: Valor contratado (R$) | O4: Data da OF/OS | P4: Dias úteis DFD→OF | Q4: Data do recebimento | R4: Nota de avaliação (1-5) | S4: Data do pagamento | T4: Urgência? | U4: Modo aplicado | V4: Nº propostas | W4: Dossiê completo? | X4: Observações
A5: 2026-BM-001 | B5: 46310 | C5: Baile da Memória 60+ (TF SEMESQV) | D5: L01 | E5: 200 kits lanche para o baile de outubro | F5: 3900 | G5: =IF(F5="","",IF(F5<=Parâmetros!$B$7,"Faixa 1",IF(F5<=Parâmetros!$B$8,"Faixa 2","Faixa 3"))) -> Faixa 1 | H5: =IF(G5="","",IF(G5="Faixa 1","Rodízio/Sorteio",IF(G5="Faixa 2","Cotação (≥3 propostas)","Chamada pública"))) -> Rodízio/Sorteio | I5: F001 | J5: =IF(I5="","",IFERROR(INDEX(Cadastro!$B$5:$B$304,MATCH(I5,Cadastro!$A$5:$A$304,0)),"ID não encontrado")) -> Maria das Dores Lanches ME | K5: =IF(I5="","",IFERROR(INDEX(Cadastro!$E$5:$E$304,MATCH(I5,Cadastro!$A$5:$A$304,0)),"")) -> S | L5: =IF(I5="","",IFERROR(INDEX(Cadastro!$F$5:$F$304,MATCH(I5,Cadastro!$A$5:$A$304,0)),"")) -> S | M5: =IF(I5="","",IFERROR(INDEX(Cadastro!$I$5:$I$304,MATCH(I5,Cadastro!$A$5:$A$304,0)),"")) -> T1 | N5: 3850 | O5: 46315 | P5: =IF(OR(B5="",O5=""),"",NETWORKDAYS(B5,O5)-1) -> 3 | Q5: 46320 | R5: 5 | S5: 46331 | T5: N | U5: Rodízio | V5: 1 | W5: S | X5: EXEMPLO — apagar
A6: 2026-BM-002 | B6: 46311 | C6: Baile da Memória 60+ (TF SEMESQV) | D6: L03 | E6: Sonorização e iluminação — palco 6x4, 6h | F6: 18000 | G6: =IF(F6="","",IF(F6<=Parâmetros!$B$7,"Faixa 1",IF(F6<=Parâmetros!$B$8,"Faixa 2","Faixa 3"))) -> Faixa 2 | H6: =IF(G6="","",IF(G6="Faixa 1","Rodízio/Sorteio",IF(G6="Faixa 2","Cotação (≥3 propostas)","Chamada pública"))) -> Cotação (≥3 propostas) | I6: F002 | J6: =IF(I6="","",IFERROR(INDEX(Cadastro!$B$5:$B$304,MATCH(I6,Cadastro!$A$5:$A$304,0)),"ID não encontrado")) -> João Som & Luz MEI | K6: =IF(I6="","",IFERROR(INDEX(Cadastro!$E$5:$E$304,MATCH(I6,Cadastro!$A$5:$A$304,0)),"")) -> S | L6: =IF(I6="","",IFERROR(INDEX(Cadastro!$F$5:$F$304,MATCH(I6,Cadastro!$A$5:$A$304,0)),"")) -> N | M6: =IF(I6="","",IFERROR(INDEX(Cadastro!$I$5:$I$304,MATCH(I6,Cadastro!$A$5:$A$304,0)),"")) -> T2 | N6: 17200 | O6: 46318 | P6: =IF(OR(B6="",O6=""),"",NETWORKDAYS(B6,O6)-1) -> 5 | Q6: 46320 | R6: 4 | S6: 46336 | T6: N | U6: Cotação | V6: 4 | W6: S | X6: EXEMPLO — apagar
A7: 2026-EC-003 | B7: 46315 | C7: Economia Criativa 60+ | D7: L12 | E7: Kits de artesanato para 120 participantes | F7: 9600 | G7: =IF(F7="","",IF(F7<=Parâmetros!$B$7,"Faixa 1",IF(F7<=Parâmetros!$B$8,"Faixa 2","Faixa 3"))) -> Faixa 1 | H7: =IF(G7="","",IF(G7="Faixa 1","Rodízio/Sorteio",IF(G7="Faixa 2","Cotação (≥3 propostas)","Chamada pública"))) -> Rodízio/Sorteio | I7: F003 | J7: =IF(I7="","",IFERROR(INDEX(Cadastro!$B$5:$B$304,MATCH(I7,Cadastro!$A$5:$A$304,0)),"ID não encontrado")) -> Coletivo Mãos de Mesquita (cooperativa) | K7: =IF(I7="","",IFERROR(INDEX(Cadastro!$E$5:$E$304,MATCH(I7,Cadastro!$A$5:$A$304,0)),"")) -> S | L7: =IF(I7="","",IFERROR(INDEX(Cadastro!$F$5:$F$304,MATCH(I7,Cadastro!$A$5:$A$304,0)),"")) -> S | M7: =IF(I7="","",IFERROR(INDEX(Cadastro!$I$5:$I$304,MATCH(I7,Cadastro!$A$5:$A$304,0)),"")) -> T1 | N7: 9600 | O7: 46317 | P7: =IF(OR(B7="",O7=""),"",NETWORKDAYS(B7,O7)-1) -> 2 | Q7: 46328 | R7: 5 | S7: 46338 | T7: N | U7: Rodízio | V7: 1 | W7: S | X7: EXEMPLO — apagar
A8: 2026-JL-004 | B8: 46329 | C8: Jogos da Longevidade 60+ | D8: L07 | E8: Oficina de dança sênior — 8 encontros | F8: 4000 | G8: =IF(F8="","",IF(F8<=Parâmetros!$B$7,"Faixa 1",IF(F8<=Parâmetros!$B$8,"Faixa 2","Faixa 3"))) -> Faixa 1 | H8: =IF(G8="","",IF(G8="Faixa 1","Rodízio/Sorteio",IF(G8="Faixa 2","Cotação (≥3 propostas)","Chamada pública"))) -> Rodízio/Sorteio | I8: F004 | J8: =IF(I8="","",IFERROR(INDEX(Cadastro!$B$5:$B$304,MATCH(I8,Cadastro!$A$5:$A$304,0)),"ID não encontrado")) -> Ana Paula Silva (oficineira) | K8: =IF(I8="","",IFERROR(INDEX(Cadastro!$E$5:$E$304,MATCH(I8,Cadastro!$A$5:$A$304,0)),"")) -> S | L8: =IF(I8="","",IFERROR(INDEX(Cadastro!$F$5:$F$304,MATCH(I8,Cadastro!$A$5:$A$304,0)),"")) -> S | M8: =IF(I8="","",IFERROR(INDEX(Cadastro!$I$5:$I$304,MATCH(I8,Cadastro!$A$5:$A$304,0)),"")) -> T1 | N8: 4000 | O8: 46331 | P8: =IF(OR(B8="",O8=""),"",NETWORKDAYS(B8,O8)-1) -> 2 | Q8: 46366 | R8: 5 | S8: 46374 | T8: N | U8: Rodízio | V8: 1 | W8: S | X8: EXEMPLO — apagar
A9: 2026-JL-005 | B9: 46330 | C9: Jogos da Longevidade 60+ | D9: L10 | E9: Banners, faixas e 500 crachás | F9: 6200 | G9: =IF(F9="","",IF(F9<=Parâmetros!$B$7,"Faixa 1",IF(F9<=Parâmetros!$B$8,"Faixa 2","Faixa 3"))) -> Faixa 1 | H9: =IF(G9="","",IF(G9="Faixa 1","Rodízio/Sorteio",IF(G9="Faixa 2","Cotação (≥3 propostas)","Chamada pública"))) -> Rodízio/Sorteio | I9: F005 | J9: =IF(I9="","",IFERROR(INDEX(Cadastro!$B$5:$B$304,MATCH(I9,Cadastro!$A$5:$A$304,0)),"ID não encontrado")) -> Gráfica Baixada EPP | K9: =IF(I9="","",IFERROR(INDEX(Cadastro!$E$5:$E$304,MATCH(I9,Cadastro!$A$5:$A$304,0)),"")) -> S | L9: =IF(I9="","",IFERROR(INDEX(Cadastro!$F$5:$F$304,MATCH(I9,Cadastro!$A$5:$A$304,0)),"")) -> N | M9: =IF(I9="","",IFERROR(INDEX(Cadastro!$I$5:$I$304,MATCH(I9,Cadastro!$A$5:$A$304,0)),"")) -> T2 | N9: 5900 | O9: 46332 | P9: =IF(OR(B9="",O9=""),"",NETWORKDAYS(B9,O9)-1) -> 2 | Q9: 46346 | R9: 3 | S9: 46357 | T9: S | U9: Urgência | V9: 1 | W9: N | X9: EXEMPLO — apagar (urgência: fornecedor anterior desistiu)
G10: =IF(F10="","",IF(F10<=Parâmetros!$B$7,"Faixa 1",IF(F10<=Parâmetros!$B$8,"Faixa 2","Faixa 3"))) | H10: =IF(G10="","",IF(G10="Faixa 1","Rodízio/Sorteio",IF(G10="Faixa 2","Cotação (≥3 propostas)","Chamada pública"))) | J10: =IF(I10="","",IFERROR(INDEX(Cadastro!$B$5:$B$304,MATCH(I10,Cadastro!$A$5:$A$304,0)),"ID não encontrado")) | K10: =IF(I10="","",IFERROR(INDEX(Cadastro!$E$5:$E$304,MATCH(I10,Cadastro!$A$5:$A$304,0)),"")) | L10: =IF(I10="","",IFERROR(INDEX(Cadastro!$F$5:$F$304,MATCH(I10,Cadastro!$A$5:$A$304,0)),"")) | M10: =IF(I10="","",IFERROR(INDEX(Cadastro!$I$5:$I$304,MATCH(I10,Cadastro!$A$5:$A$304,0)),"")) | P10: =IF(OR(B10="",O10=""),"",NETWORKDAYS(B10,O10)-1)
G11: =IF(F11="","",IF(F11<=Parâmetros!$B$7,"Faixa 1",IF(F11<=Parâmetros!$B$8,"Faixa 2","Faixa 3"))) | H11: =IF(G11="","",IF(G11="Faixa 1","Rodízio/Sorteio",IF(G11="Faixa 2","Cotação (≥3 propostas)","Chamada pública"))) | J11: =IF(I11="","",IFERROR(INDEX(Cadastro!$B$5:$B$304,MATCH(I11,Cadastro!$A$5:$A$304,0)),"ID não encontrado")) | K11: =IF(I11="","",IFERROR(INDEX(Cadastro!$E$5:$E$304,MATCH(I11,Cadastro!$A$5:$A$304,0)),"")) | L11: =IF(I11="","",IFERROR(INDEX(Cadastro!$F$5:$F$304,MATCH(I11,Cadastro!$A$5:$A$304,0)),"")) | M11: =IF(I11="","",IFERROR(INDEX(Cadastro!$I$5:$I$304,MATCH(I11,Cadastro!$A$5:$A$304,0)),"")) | P11: =IF(OR(B11="",O11=""),"",NETWORKDAYS(B11,O11)-1)
G12: =IF(F12="","",IF(F12<=Parâmetros!$B$7,"Faixa 1",IF(F12<=Parâmetros!$B$8,"Faixa 2","Faixa 3"))) | H12: =IF(G12="","",IF(G12="Faixa 1","Rodízio/Sorteio",IF(G12="Faixa 2","Cotação (≥3 propostas)","Chamada pública"))) | J12: =IF(I12="","",IFERROR(INDEX(Cadastro!$B$5:$B$304,MATCH(I12,Cadastro!$A$5:$A$304,0)),"ID não encontrado")) | K12: =IF(I12="","",IFERROR(INDEX(Cadastro!$E$5:$E$304,MATCH(I12,Cadastro!$A$5:$A$304,0)),"")) | L12: =IF(I12="","",IFERROR(INDEX(Cadastro!$F$5:$F$304,MATCH(I12,Cadastro!$A$5:$A$304,0)),"")) | M12: =IF(I12="","",IFERROR(INDEX(Cadastro!$I$5:$I$304,MATCH(I12,Cadastro!$A$5:$A$304,0)),"")) | P12: =IF(OR(B12="",O12=""),"",NETWORKDAYS(B12,O12)-1)
G13: =IF(F13="","",IF(F13<=Parâmetros!$B$7,"Faixa 1",IF(F13<=Parâmetros!$B$8,"Faixa 2","Faixa 3"))) | H13: =IF(G13="","",IF(G13="Faixa 1","Rodízio/Sorteio",IF(G13="Faixa 2","Cotação (≥3 propostas)","Chamada pública"))) | J13: =IF(I13="","",IFERROR(INDEX(Cadastro!$B$5:$B$304,MATCH(I13,Cadastro!$A$5:$A$304,0)),"ID não encontrado")) | K13: =IF(I13="","",IFERROR(INDEX(Cadastro!$E$5:$E$304,MATCH(I13,Cadastro!$A$5:$A$304,0)),"")) | L13: =IF(I13="","",IFERROR(INDEX(Cadastro!$F$5:$F$304,MATCH(I13,Cadastro!$A$5:$A$304,0)),"")) | M13: =IF(I13="","",IFERROR(INDEX(Cadastro!$I$5:$I$304,MATCH(I13,Cadastro!$A$5:$A$304,0)),"")) | P13: =IF(OR(B13="",O13=""),"",NETWORKDAYS(B13,O13)-1)
G14: =IF(F14="","",IF(F14<=Parâmetros!$B$7,"Faixa 1",IF(F14<=Parâmetros!$B$8,"Faixa 2","Faixa 3"))) | H14: =IF(G14="","",IF(G14="Faixa 1","Rodízio/Sorteio",IF(G14="Faixa 2","Cotação (≥3 propostas)","Chamada pública"))) | J14: =IF(I14="","",IFERROR(INDEX(Cadastro!$B$5:$B$304,MATCH(I14,Cadastro!$A$5:$A$304,0)),"ID não encontrado")) | K14: =IF(I14="","",IFERROR(INDEX(Cadastro!$E$5:$E$304,MATCH(I14,Cadastro!$A$5:$A$304,0)),"")) | L14: =IF(I14="","",IFERROR(INDEX(Cadastro!$F$5:$F$304,MATCH(I14,Cadastro!$A$5:$A$304,0)),"")) | M14: =IF(I14="","",IFERROR(INDEX(Cadastro!$I$5:$I$304,MATCH(I14,Cadastro!$A$5:$A$304,0)),"")) | P14: =IF(OR(B14="",O14=""),"",NETWORKDAYS(B14,O14)-1)
G15: =IF(F15="","",IF(F15<=Parâmetros!$B$7,"Faixa 1",IF(F15<=Parâmetros!$B$8,"Faixa 2","Faixa 3"))) | H15: =IF(G15="","",IF(G15="Faixa 1","Rodízio/Sorteio",IF(G15="Faixa 2","Cotação (≥3 propostas)","Chamada pública"))) | J15: =IF(I15="","",IFERROR(INDEX(Cadastro!$B$5:$B$304,MATCH(I15,Cadastro!$A$5:$A$304,0)),"ID não encontrado")) | K15: =IF(I15="","",IFERROR(INDEX(Cadastro!$E$5:$E$304,MATCH(I15,Cadastro!$A$5:$A$304,0)),"")) | L15: =IF(I15="","",IFERROR(INDEX(Cadastro!$F$5:$F$304,MATCH(I15,Cadastro!$A$5:$A$304,0)),"")) | M15: =IF(I15="","",IFERROR(INDEX(Cadastro!$I$5:$I$304,MATCH(I15,Cadastro!$A$5:$A$304,0)),"")) | P15: =IF(OR(B15="",O15=""),"",NETWORKDAYS(B15,O15)-1)
G16: =IF(F16="","",IF(F16<=Parâmetros!$B$7,"Faixa 1",IF(F16<=Parâmetros!$B$8,"Faixa 2","Faixa 3"))) | H16: =IF(G16="","",IF(G16="Faixa 1","Rodízio/Sorteio",IF(G16="Faixa 2","Cotação (≥3 propostas)","Chamada pública"))) | J16: =IF(I16="","",IFERROR(INDEX(Cadastro!$B$5:$B$304,MATCH(I16,Cadastro!$A$5:$A$304,0)),"ID não encontrado")) | K16: =IF(I16="","",IFERROR(INDEX(Cadastro!$E$5:$E$304,MATCH(I16,Cadastro!$A$5:$A$304,0)),"")) | L16: =IF(I16="","",IFERROR(INDEX(Cadastro!$F$5:$F$304,MATCH(I16,Cadastro!$A$5:$A$304,0)),"")) | M16: =IF(I16="","",IFERROR(INDEX(Cadastro!$I$5:$I$304,MATCH(I16,Cadastro!$A$5:$A$304,0)),"")) | P16: =IF(OR(B16="",O16=""),"",NETWORKDAYS(B16,O16)-1)
G17: =IF(F17="","",IF(F17<=Parâmetros!$B$7,"Faixa 1",IF(F17<=Parâmetros!$B$8,"Faixa 2","Faixa 3"))) | H17: =IF(G17="","",IF(G17="Faixa 1","Rodízio/Sorteio",IF(G17="Faixa 2","Cotação (≥3 propostas)","Chamada pública"))) | J17: =IF(I17="","",IFERROR(INDEX(Cadastro!$B$5:$B$304,MATCH(I17,Cadastro!$A$5:$A$304,0)),"ID não encontrado")) | K17: =IF(I17="","",IFERROR(INDEX(Cadastro!$E$5:$E$304,MATCH(I17,Cadastro!$A$5:$A$304,0)),"")) | L17: =IF(I17="","",IFERROR(INDEX(Cadastro!$F$5:$F$304,MATCH(I17,Cadastro!$A$5:$A$304,0)),"")) | M17: =IF(I17="","",IFERROR(INDEX(Cadastro!$I$5:$I$304,MATCH(I17,Cadastro!$A$5:$A$304,0)),"")) | P17: =IF(OR(B17="",O17=""),"",NETWORKDAYS(B17,O17)-1)
G18: =IF(F18="","",IF(F18<=Parâmetros!$B$7,"Faixa 1",IF(F18<=Parâmetros!$B$8,"Faixa 2","Faixa 3"))) | H18: =IF(G18="","",IF(G18="Faixa 1","Rodízio/Sorteio",IF(G18="Faixa 2","Cotação (≥3 propostas)","Chamada pública"))) | J18: =IF(I18="","",IFERROR(INDEX(Cadastro!$B$5:$B$304,MATCH(I18,Cadastro!$A$5:$A$304,0)),"ID não encontrado")) | K18: =IF(I18="","",IFERROR(INDEX(Cadastro!$E$5:$E$304,MATCH(I18,Cadastro!$A$5:$A$304,0)),"")) | L18: =IF(I18="","",IFERROR(INDEX(Cadastro!$F$5:$F$304,MATCH(I18,Cadastro!$A$5:$A$304,0)),"")) | M18: =IF(I18="","",IFERROR(INDEX(Cadastro!$I$5:$I$304,MATCH(I18,Cadastro!$A$5:$A$304,0)),"")) | P18: =IF(OR(B18="",O18=""),"",NETWORKDAYS(B18,O18)-1)
G19: =IF(F19="","",IF(F19<=Parâmetros!$B$7,"Faixa 1",IF(F19<=Parâmetros!$B$8,"Faixa 2","Faixa 3"))) | H19: =IF(G19="","",IF(G19="Faixa 1","Rodízio/Sorteio",IF(G19="Faixa 2","Cotação (≥3 propostas)","Chamada pública"))) | J19: =IF(I19="","",IFERROR(INDEX(Cadastro!$B$5:$B$304,MATCH(I19,Cadastro!$A$5:$A$304,0)),"ID não encontrado")) | K19: =IF(I19="","",IFERROR(INDEX(Cadastro!$E$5:$E$304,MATCH(I19,Cadastro!$A$5:$A$304,0)),"")) | L19: =IF(I19="","",IFERROR(INDEX(Cadastro!$F$5:$F$304,MATCH(I19,Cadastro!$A$5:$A$304,0)),"")) | M19: =IF(I19="","",IFERROR(INDEX(Cadastro!$I$5:$I$304,MATCH(I19,Cadastro!$A$5:$A$304,0)),"")) | P19: =IF(OR(B19="",O19=""),"",NETWORKDAYS(B19,O19)-1)
G20: =IF(F20="","",IF(F20<=Parâmetros!$B$7,"Faixa 1",IF(F20<=Parâmetros!$B$8,"Faixa 2","Faixa 3"))) | H20: =IF(G20="","",IF(G20="Faixa 1","Rodízio/Sorteio",IF(G20="Faixa 2","Cotação (≥3 propostas)","Chamada pública"))) | J20: =IF(I20="","",IFERROR(INDEX(Cadastro!$B$5:$B$304,MATCH(I20,Cadastro!$A$5:$A$304,0)),"ID não encontrado")) | K20: =IF(I20="","",IFERROR(INDEX(Cadastro!$E$5:$E$304,MATCH(I20,Cadastro!$A$5:$A$304,0)),"")) | L20: =IF(I20="","",IFERROR(INDEX(Cadastro!$F$5:$F$304,MATCH(I20,Cadastro!$A$5:$A$304,0)),"")) | M20: =IF(I20="","",IFERROR(INDEX(Cadastro!$I$5:$I$304,MATCH(I20,Cadastro!$A$5:$A$304,0)),"")) | P20: =IF(OR(B20="",O20=""),"",NETWORKDAYS(B20,O20)-1)
G21: =IF(F21="","",IF(F21<=Parâmetros!$B$7,"Faixa 1",IF(F21<=Parâmetros!$B$8,"Faixa 2","Faixa 3"))) | H21: =IF(G21="","",IF(G21="Faixa 1","Rodízio/Sorteio",IF(G21="Faixa 2","Cotação (≥3 propostas)","Chamada pública"))) | J21: =IF(I21="","",IFERROR(INDEX(Cadastro!$B$5:$B$304,MATCH(I21,Cadastro!$A$5:$A$304,0)),"ID não encontrado")) | K21: =IF(I21="","",IFERROR(INDEX(Cadastro!$E$5:$E$304,MATCH(I21,Cadastro!$A$5:$A$304,0)),"")) | L21: =IF(I21="","",IFERROR(INDEX(Cadastro!$F$5:$F$304,MATCH(I21,Cadastro!$A$5:$A$304,0)),"")) | M21: =IF(I21="","",IFERROR(INDEX(Cadastro!$I$5:$I$304,MATCH(I21,Cadastro!$A$5:$A$304,0)),"")) | P21: =IF(OR(B21="",O21=""),"",NETWORKDAYS(B21,O21)-1)
... G504: =IF(F504="","",IF(F504<=Parâmetros!$B$7,"Faixa 1",IF(F504<=Parâmetros!$B$8,"Faixa 2","Faixa 3"))) | H504: =IF(G504="","",IF(G504="Faixa 1","Rodízio/Sorteio",IF(G504="Faixa 2","Cotação (≥3 propostas)","Chamada pública"))) | J504: =IF(I504="","",IFERROR(INDEX(Cadastro!$B$5:$B$304,MATCH(I504,Cadastro!$A$5:$A$304,0)),"ID não encontrado")) | K504: =IF(I504="","",IFERROR(INDEX(Cadastro!$E$5:$E$304,MATCH(I504,Cadastro!$A$5:$A$304,0)),"")) | L504: =IF(I504="","",IFERROR(INDEX(Cadastro!$F$5:$F$304,MATCH(I504,Cadastro!$A$5:$A$304,0)),"")) | M504: =IF(I504="","",IFERROR(INDEX(Cadastro!$I$5:$I$304,MATCH(I504,Cadastro!$A$5:$A$304,0)),"")) | P504: =IF(OR(B504="",O504=""),"",NETWORKDAYS(B504,O504)-1)

Sheet Rodízio
A1: Rodízio — próximo credenciado da linha (Faixa 1)
A2: Informe a linha e o território nas células amarelas. A tabela lista os credenciados ativos elegíveis; o "Próximo" é quem está há mais tempo sem contratação (nunca contratado primeiro; empate: credenciamento mais antigo).
A4: Linha de fornecimento | B4: L01 | D4: PRÓXIMO DO RODÍZIO
A5: Território | B5: T1 | D5: =IFERROR(INDEX(B10:B309,MATCH(1,I10:I309,0)),"nenhum elegível") -> Maria das Dores Lanches ME
A6: Somente pequenos negócios? (S/N) | B6: S | D6: Elegíveis na linha/território: | E6: =SUM(F10:F309) -> 1
A7: Somente negócios liderados por mulheres? (S/N) | B7: N | D7: Exclusividade a pequenos negócios cabível (≥3)? | E7: =IF(SUMPRODUCT((F10:F309=1)*(Cadastro!E5:E304="S"))>=Parâmetros!$B$19,"SIM","NÃO") -> NÃO
A9: ID | B9: Fornecedor | C9: Porte | D9: Mulher? | E9: Território | F9: Elegível (1/0) | G9: Última contratação | H9: Ordem no rodízio | I9: É o próximo? | J9: chave (auxiliar)
A10: =IF(Cadastro!A5="","",Cadastro!A5) -> F001 | B10: =IF(Cadastro!A5="","",Cadastro!B5) -> Maria das Dores Lanches ME | C10: =IF(Cadastro!A5="","",Cadastro!D5) -> ME | D10: =IF(Cadastro!A5="","",Cadastro!F5) -> S | E10: =IF(Cadastro!A5="","",Cadastro!I5) -> T1 | F10: =IF(Cadastro!A5="",0,IF(AND(Cadastro!O5="Ativo",Cadastro!I5=$B$5,ISNUMBER(SEARCH($B$4,Cadastro!J5)),OR($B$6<>"S",Cadastro!E5="S"),OR($B$7<>"S",Cadastro!F5="S")),1,0)) -> 1 | G10: =IF(F10=0,"",IF(Cadastro!U5=0,0,Cadastro!X5)) -> 46315 | H10: =IF(F10=0,"",1+COUNTIF($J$10:$J$309,"<"&J10)) -> 1 | I10: =IF(H10=1,1,0) -> 1 | J10: =IF(F10=0,9000000000000000,G10+Cadastro!M5/100000) -> 46315.463
A11: =IF(Cadastro!A6="","",Cadastro!A6) -> F002 | B11: =IF(Cadastro!A6="","",Cadastro!B6) -> João Som & Luz MEI | C11: =IF(Cadastro!A6="","",Cadastro!D6) -> MEI | D11: =IF(Cadastro!A6="","",Cadastro!F6) -> N | E11: =IF(Cadastro!A6="","",Cadastro!I6) -> T2 | F11: =IF(Cadastro!A6="",0,IF(AND(Cadastro!O6="Ativo",Cadastro!I6=$B$5,ISNUMBER(SEARCH($B$4,Cadastro!J6)),OR($B$6<>"S",Cadastro!E6="S"),OR($B$7<>"S",Cadastro!F6="S")),1,0)) -> 0 | G11: =IF(F11=0,"",IF(Cadastro!U6=0,0,Cadastro!X6)) | H11: =IF(F11=0,"",1+COUNTIF($J$10:$J$309,"<"&J11)) | I11: =IF(H11=1,1,0) -> 0 | J11: =IF(F11=0,9000000000000000,G11+Cadastro!M6/100000) -> 9e+15
A12: =IF(Cadastro!A7="","",Cadastro!A7) -> F003 | B12: =IF(Cadastro!A7="","",Cadastro!B7) -> Coletivo Mãos de Mesquita (cooperativa) | C12: =IF(Cadastro!A7="","",Cadastro!D7) -> Cooperativa | D12: =IF(Cadastro!A7="","",Cadastro!F7) -> S | E12: =IF(Cadastro!A7="","",Cadastro!I7) -> T1 | F12: =IF(Cadastro!A7="",0,IF(AND(Cadastro!O7="Ativo",Cadastro!I7=$B$5,ISNUMBER(SEARCH($B$4,Cadastro!J7)),OR($B$6<>"S",Cadastro!E7="S"),OR($B$7<>"S",Cadastro!F7="S")),1,0)) -> 0 | G12: =IF(F12=0,"",IF(Cadastro!U7=0,0,Cadastro!X7)) | H12: =IF(F12=0,"",1+COUNTIF($J$10:$J$309,"<"&J12)) | I12: =IF(H12=1,1,0) -> 0 | J12: =IF(F12=0,9000000000000000,G12+Cadastro!M7/100000) -> 9e+15
A13: =IF(Cadastro!A8="","",Cadastro!A8) -> F004 | B13: =IF(Cadastro!A8="","",Cadastro!B8) -> Ana Paula Silva (oficineira) | C13: =IF(Cadastro!A8="","",Cadastro!D8) -> PF autônoma | D13: =IF(Cadastro!A8="","",Cadastro!F8) -> S | E13: =IF(Cadastro!A8="","",Cadastro!I8) -> T1 | F13: =IF(Cadastro!A8="",0,IF(AND(Cadastro!O8="Ativo",Cadastro!I8=$B$5,ISNUMBER(SEARCH($B$4,Cadastro!J8)),OR($B$6<>"S",Cadastro!E8="S"),OR($B$7<>"S",Cadastro!F8="S")),1,0)) -> 0 | G13: =IF(F13=0,"",IF(Cadastro!U8=0,0,Cadastro!X8)) | H13: =IF(F13=0,"",1+COUNTIF($J$10:$J$309,"<"&J13)) | I13: =IF(H13=1,1,0) -> 0 | J13: =IF(F13=0,9000000000000000,G13+Cadastro!M8/100000) -> 9e+15
A14: =IF(Cadastro!A9="","",Cadastro!A9) -> F005 | B14: =IF(Cadastro!A9="","",Cadastro!B9) -> Gráfica Baixada EPP | C14: =IF(Cadastro!A9="","",Cadastro!D9) -> EPP | D14: =IF(Cadastro!A9="","",Cadastro!F9) -> N | E14: =IF(Cadastro!A9="","",Cadastro!I9) -> T2 | F14: =IF(Cadastro!A9="",0,IF(AND(Cadastro!O9="Ativo",Cadastro!I9=$B$5,ISNUMBER(SEARCH($B$4,Cadastro!J9)),OR($B$6<>"S",Cadastro!E9="S"),OR($B$7<>"S",Cadastro!F9="S")),1,0)) -> 0 | G14: =IF(F14=0,"",IF(Cadastro!U9=0,0,Cadastro!X9)) | H14: =IF(F14=0,"",1+COUNTIF($J$10:$J$309,"<"&J14)) | I14: =IF(H14=1,1,0) -> 0 | J14: =IF(F14=0,9000000000000000,G14+Cadastro!M9/100000) -> 9e+15
A15: =IF(Cadastro!A10="","",Cadastro!A10) -> F006 | B15: =IF(Cadastro!A10="","",Cadastro!B10) -> Lanches da Tia Rosa MEI | C15: =IF(Cadastro!A10="","",Cadastro!D10) -> MEI | D15: =IF(Cadastro!A10="","",Cadastro!F10) -> S | E15: =IF(Cadastro!A10="","",Cadastro!I10) -> T1 | F15: =IF(Cadastro!A10="",0,IF(AND(Cadastro!O10="Ativo",Cadastro!I10=$B$5,ISNUMBER(SEARCH($B$4,Cadastro!J10)),OR($B$6<>"S",Cadastro!E10="S"),OR($B$7<>"S",Cadastro!F10="S")),1,0)) -> 0 | G15: =IF(F15=0,"",IF(Cadastro!U10=0,0,Cadastro!X10)) | H15: =IF(F15=0,"",1+COUNTIF($J$10:$J$309,"<"&J15)) | I15: =IF(H15=1,1,0) -> 0 | J15: =IF(F15=0,9000000000000000,G15+Cadastro!M10/100000) -> 9e+15
A16: =IF(Cadastro!A11="","",Cadastro!A11) | B16: =IF(Cadastro!A11="","",Cadastro!B11) | C16: =IF(Cadastro!A11="","",Cadastro!D11) | D16: =IF(Cadastro!A11="","",Cadastro!F11) | E16: =IF(Cadastro!A11="","",Cadastro!I11) | F16: =IF(Cadastro!A11="",0,IF(AND(Cadastro!O11="Ativo",Cadastro!I11=$B$5,ISNUMBER(SEARCH($B$4,Cadastro!J11)),OR($B$6<>"S",Cadastro!E11="S"),OR($B$7<>"S",Cadastro!F11="S")),1,0)) -> 0 | G16: =IF(F16=0,"",IF(Cadastro!U11=0,0,Cadastro!X11)) | H16: =IF(F16=0,"",1+COUNTIF($J$10:$J$309,"<"&J16)) | I16: =IF(H16=1,1,0) -> 0 | J16: =IF(F16=0,9000000000000000,G16+Cadastro!M11/100000) -> 9e+15
A17: =IF(Cadastro!A12="","",Cadastro!A12) | B17: =IF(Cadastro!A12="","",Cadastro!B12) | C17: =IF(Cadastro!A12="","",Cadastro!D12) | D17: =IF(Cadastro!A12="","",Cadastro!F12) | E17: =IF(Cadastro!A12="","",Cadastro!I12) | F17: =IF(Cadastro!A12="",0,IF(AND(Cadastro!O12="Ativo",Cadastro!I12=$B$5,ISNUMBER(SEARCH($B$4,Cadastro!J12)),OR($B$6<>"S",Cadastro!E12="S"),OR($B$7<>"S",Cadastro!F12="S")),1,0)) -> 0 | G17: =IF(F17=0,"",IF(Cadastro!U12=0,0,Cadastro!X12)) | H17: =IF(F17=0,"",1+COUNTIF($J$10:$J$309,"<"&J17)) | I17: =IF(H17=1,1,0) -> 0 | J17: =IF(F17=0,9000000000000000,G17+Cadastro!M12/100000) -> 9e+15
A18: =IF(Cadastro!A13="","",Cadastro!A13) | B18: =IF(Cadastro!A13="","",Cadastro!B13) | C18: =IF(Cadastro!A13="","",Cadastro!D13) | D18: =IF(Cadastro!A13="","",Cadastro!F13) | E18: =IF(Cadastro!A13="","",Cadastro!I13) | F18: =IF(Cadastro!A13="",0,IF(AND(Cadastro!O13="Ativo",Cadastro!I13=$B$5,ISNUMBER(SEARCH($B$4,Cadastro!J13)),OR($B$6<>"S",Cadastro!E13="S"),OR($B$7<>"S",Cadastro!F13="S")),1,0)) -> 0 | G18: =IF(F18=0,"",IF(Cadastro!U13=0,0,Cadastro!X13)) | H18: =IF(F18=0,"",1+COUNTIF($J$10:$J$309,"<"&J18)) | I18: =IF(H18=1,1,0) -> 0 | J18: =IF(F18=0,9000000000000000,G18+Cadastro!M13/100000) -> 9e+15
A19: =IF(Cadastro!A14="","",Cadastro!A14) | B19: =IF(Cadastro!A14="","",Cadastro!B14) | C19: =IF(Cadastro!A14="","",Cadastro!D14) | D19: =IF(Cadastro!A14="","",Cadastro!F14) | E19: =IF(Cadastro!A14="","",Cadastro!I14) | F19: =IF(Cadastro!A14="",0,IF(AND(Cadastro!O14="Ativo",Cadastro!I14=$B$5,ISNUMBER(SEARCH($B$4,Cadastro!J14)),OR($B$6<>"S",Cadastro!E14="S"),OR($B$7<>"S",Cadastro!F14="S")),1,0)) -> 0 | G19: =IF(F19=0,"",IF(Cadastro!U14=0,0,Cadastro!X14)) | H19: =IF(F19=0,"",1+COUNTIF($J$10:$J$309,"<"&J19)) | I19: =IF(H19=1,1,0) -> 0 | J19: =IF(F19=0,9000000000000000,G19+Cadastro!M14/100000) -> 9e+15
A20: =IF(Cadastro!A15="","",Cadastro!A15) | B20: =IF(Cadastro!A15="","",Cadastro!B15) | C20: =IF(Cadastro!A15="","",Cadastro!D15) | D20: =IF(Cadastro!A15="","",Cadastro!F15) | E20: =IF(Cadastro!A15="","",Cadastro!I15) | F20: =IF(Cadastro!A15="",0,IF(AND(Cadastro!O15="Ativo",Cadastro!I15=$B$5,ISNUMBER(SEARCH($B$4,Cadastro!J15)),OR($B$6<>"S",Cadastro!E15="S"),OR($B$7<>"S",Cadastro!F15="S")),1,0)) -> 0 | G20: =IF(F20=0,"",IF(Cadastro!U15=0,0,Cadastro!X15)) | H20: =IF(F20=0,"",1+COUNTIF($J$10:$J$309,"<"&J20)) | I20: =IF(H20=1,1,0) -> 0 | J20: =IF(F20=0,9000000000000000,G20+Cadastro!M15/100000) -> 9e+15
A21: =IF(Cadastro!A16="","",Cadastro!A16) | B21: =IF(Cadastro!A16="","",Cadastro!B16) | C21: =IF(Cadastro!A16="","",Cadastro!D16) | D21: =IF(Cadastro!A16="","",Cadastro!F16) | E21: =IF(Cadastro!A16="","",Cadastro!I16) | F21: =IF(Cadastro!A16="",0,IF(AND(Cadastro!O16="Ativo",Cadastro!I16=$B$5,ISNUMBER(SEARCH($B$4,Cadastro!J16)),OR($B$6<>"S",Cadastro!E16="S"),OR($B$7<>"S",Cadastro!F16="S")),1,0)) -> 0 | G21: =IF(F21=0,"",IF(Cadastro!U16=0,0,Cadastro!X16)) | H21: =IF(F21=0,"",1+COUNTIF($J$10:$J$309,"<"&J21)) | I21: =IF(H21=1,1,0) -> 0 | J21: =IF(F21=0,9000000000000000,G21+Cadastro!M16/100000) -> 9e+15
... A309: =IF(Cadastro!A304="","",Cadastro!A304) | B309: =IF(Cadastro!A304="","",Cadastro!B304) | C309: =IF(Cadastro!A304="","",Cadastro!D304) | D309: =IF(Cadastro!A304="","",Cadastro!F304) | E309: =IF(Cadastro!A304="","",Cadastro!I304) | F309: =IF(Cadastro!A304="",0,IF(AND(Cadastro!O304="Ativo",Cadastro!I304=$B$5,ISNUMBER(SEARCH($B$4,Cadastro!J304)),OR($B$6<>"S",Cadastro!E304="S"),OR($B$7<>"S",Cadastro!F304="S")),1,0)) -> 0 | G309: =IF(F309=0,"",IF(Cadastro!U304=0,0,Cadastro!X304)) | H309: =IF(F309=0,"",1+COUNTIF($J$10:$J$309,"<"&J309)) | I309: =IF(H309=1,1,0) -> 0 | J309: =IF(F309=0,9000000000000000,G309+Cadastro!M304/100000) -> 9e+15

Sheet Cotações
A1: Mapa comparativo de propostas (Faixas 2 e 3)
A2: Digite o ID do fornecedor e o valor de cada proposta. A planilha aplica: menor preço → empate ficto (pequenos negócios) → preferência local → desempate por equidade. Confirme o resultado em ata; o "direito de cobrir" deve ser exercido pelo fornecedor indicado.
A4: Oportunidade nº | B4: EXEMPLO — apagar | D4: Menor preço válido | E4: =IF(COUNT(C11:C22)=0,"",MIN(C11:C22)) -> 3850
A5: Linha | B5: L01 | D5: Propostas válidas | E5: =COUNT(C11:C22) -> 3
A6: Território da execução (T1 = local) | B6: T1 | D6: Mínimo exigido (Faixa 2) atendido? | E6: =IF(E5>=Parâmetros!$B$19,"SIM","NÃO — repetir cotação ou justificar") -> SIM
A7: Objeto | B7: 200 kits lanche (exemplo do Manual, item 5) | D7: VENCEDOR SUGERIDO | E7: =IFERROR(INDEX(B11:B22,MATCH(1,M11:M22,0)),"") -> Lanches da Tia Rosa MEI
D8: Motivo | E8: =IFERROR(INDEX(N11:N22,MATCH(1,M11:M22,0)),"") -> Empate ficto + preferência local — deve cobrir o menor preço em 1 dia útil
A10: ID fornecedor | B10: Fornecedor | C10: Valor da proposta (R$) | D10: Pequeno negócio? | E10: Mulher? | F10: Mulher negra/CadÚnico? | G10: Porte | H10: Território | I10: % acima do menor | J10: Empate ficto? | K10: Candidato final (1/0) | L10: Pontuação (menor = melhor) | M10: Vencedor (1/0) | N10: Motivo
A11: F005 | B11: =IF(A11="","",IFERROR(INDEX(Cadastro!$B$5:$B$304,MATCH(A11,Cadastro!$A$5:$A$304,0)),"ID não encontrado")) -> Gráfica Baixada EPP | C11: 3900 | D11: =IF(A11="","",IFERROR(INDEX(Cadastro!$E$5:$E$304,MATCH(A11,Cadastro!$A$5:$A$304,0)),"")) -> S | E11: =IF(A11="","",IFERROR(INDEX(Cadastro!$F$5:$F$304,MATCH(A11,Cadastro!$A$5:$A$304,0)),"")) -> N | F11: =IF(A11="","",IFERROR(INDEX(Cadastro!$G$5:$G$304,MATCH(A11,Cadastro!$A$5:$A$304,0)),"")) -> N | G11: =IF(A11="","",IFERROR(INDEX(Cadastro!$D$5:$D$304,MATCH(A11,Cadastro!$A$5:$A$304,0)),"")) -> EPP | H11: =IF(A11="","",IFERROR(INDEX(Cadastro!$I$5:$I$304,MATCH(A11,Cadastro!$A$5:$A$304,0)),"")) -> T2 | I11: =IF(OR(C11="",$E$4=""),"",C11/$E$4-1) -> 0.012987013 | J11: =IF(I11="","",IF(AND(D11="S",I11>0,I11<=Parâmetros!$B$9),"S","N")) -> S | K11: =IF(I11="",0,IF(OR(I11=0,J11="S"),1,0)) -> 1 | L11: =IF(K11=0,"",VALUE(RIGHT(H11,1))*1000-IF(E11="S",100,0)-IF(F11="S",10,0)-IF(G11="MEI",1,0)-IFERROR(INDEX(Cadastro!$W$5:$W$304,MATCH(A11,Cadastro!$A$5:$A$304,0))/100,0)+I11) -> 1999.983 | M11: =IF(L11="",0,IF(L11=MIN($L$11:$L$22),1,0)) -> 0 | N11: =IF(M11=0,"",IF(I11=0,"Menor preço",IF(VALUE(RIGHT(H11,1))<VALUE(RIGHT(INDEX($H$11:$H$22,MATCH(0,$I$11:$I$22,0)),1)),"Empate ficto + preferência local — deve cobrir o menor preço em 1 dia útil","Empate ficto — deve cobrir o menor preço em 1 dia útil")))
A12: F006 | B12: =IF(A12="","",IFERROR(INDEX(Cadastro!$B$5:$B$304,MATCH(A12,Cadastro!$A$5:$A$304,0)),"ID não encontrado")) -> Lanches da Tia Rosa MEI | C12: 4200 | D12: =IF(A12="","",IFERROR(INDEX(Cadastro!$E$5:$E$304,MATCH(A12,Cadastro!$A$5:$A$304,0)),"")) -> S | E12: =IF(A12="","",IFERROR(INDEX(Cadastro!$F$5:$F$304,MATCH(A12,Cadastro!$A$5:$A$304,0)),"")) -> S | F12: =IF(A12="","",IFERROR(INDEX(Cadastro!$G$5:$G$304,MATCH(A12,Cadastro!$A$5:$A$304,0)),"")) -> S | G12: =IF(A12="","",IFERROR(INDEX(Cadastro!$D$5:$D$304,MATCH(A12,Cadastro!$A$5:$A$304,0)),"")) -> MEI | H12: =IF(A12="","",IFERROR(INDEX(Cadastro!$I$5:$I$304,MATCH(A12,Cadastro!$A$5:$A$304,0)),"")) -> T1 | I12: =IF(OR(C12="",$E$4=""),"",C12/$E$4-1) -> 0.090909091 | J12: =IF(I12="","",IF(AND(D12="S",I12>0,I12<=Parâmetros!$B$9),"S","N")) -> S | K12: =IF(I12="",0,IF(OR(I12=0,J12="S"),1,0)) -> 1 | L12: =IF(K12=0,"",VALUE(RIGHT(H12,1))*1000-IF(E12="S",100,0)-IF(F12="S",10,0)-IF(G12="MEI",1,0)-IFERROR(INDEX(Cadastro!$W$5:$W$304,MATCH(A12,Cadastro!$A$5:$A$304,0))/100,0)+I12) -> 889.09091 | M12: =IF(L12="",0,IF(L12=MIN($L$11:$L$22),1,0)) -> 1 | N12: =IF(M12=0,"",IF(I12=0,"Menor preço",IF(VALUE(RIGHT(H12,1))<VALUE(RIGHT(INDEX($H$11:$H$22,MATCH(0,$I$11:$I$22,0)),1)),"Empate ficto + preferência local — deve cobrir o menor preço em 1 dia útil","Empate ficto — deve cobrir o menor preço em 1 dia útil"))) -> Empate ficto + preferência local — deve cobrir o menor preço em 1 dia útil
A13: F002 | B13: =IF(A13="","",IFERROR(INDEX(Cadastro!$B$5:$B$304,MATCH(A13,Cadastro!$A$5:$A$304,0)),"ID não encontrado")) -> João Som & Luz MEI | C13: 3850 | D13: =IF(A13="","",IFERROR(INDEX(Cadastro!$E$5:$E$304,MATCH(A13,Cadastro!$A$5:$A$304,0)),"")) -> S | E13: =IF(A13="","",IFERROR(INDEX(Cadastro!$F$5:$F$304,MATCH(A13,Cadastro!$A$5:$A$304,0)),"")) -> N | F13: =IF(A13="","",IFERROR(INDEX(Cadastro!$G$5:$G$304,MATCH(A13,Cadastro!$A$5:$A$304,0)),"")) -> N | G13: =IF(A13="","",IFERROR(INDEX(Cadastro!$D$5:$D$304,MATCH(A13,Cadastro!$A$5:$A$304,0)),"")) -> MEI | H13: =IF(A13="","",IFERROR(INDEX(Cadastro!$I$5:$I$304,MATCH(A13,Cadastro!$A$5:$A$304,0)),"")) -> T2 | I13: =IF(OR(C13="",$E$4=""),"",C13/$E$4-1) -> 0 | J13: =IF(I13="","",IF(AND(D13="S",I13>0,I13<=Parâmetros!$B$9),"S","N")) -> N | K13: =IF(I13="",0,IF(OR(I13=0,J13="S"),1,0)) -> 1 | L13: =IF(K13=0,"",VALUE(RIGHT(H13,1))*1000-IF(E13="S",100,0)-IF(F13="S",10,0)-IF(G13="MEI",1,0)-IFERROR(INDEX(Cadastro!$W$5:$W$304,MATCH(A13,Cadastro!$A$5:$A$304,0))/100,0)+I13) -> 1998.96 | M13: =IF(L13="",0,IF(L13=MIN($L$11:$L$22),1,0)) -> 0 | N13: =IF(M13=0,"",IF(I13=0,"Menor preço",IF(VALUE(RIGHT(H13,1))<VALUE(RIGHT(INDEX($H$11:$H$22,MATCH(0,$I$11:$I$22,0)),1)),"Empate ficto + preferência local — deve cobrir o menor preço em 1 dia útil","Empate ficto — deve cobrir o menor preço em 1 dia útil")))
B14: =IF(A14="","",IFERROR(INDEX(Cadastro!$B$5:$B$304,MATCH(A14,Cadastro!$A$5:$A$304,0)),"ID não encontrado")) | D14: =IF(A14="","",IFERROR(INDEX(Cadastro!$E$5:$E$304,MATCH(A14,Cadastro!$A$5:$A$304,0)),"")) | E14: =IF(A14="","",IFERROR(INDEX(Cadastro!$F$5:$F$304,MATCH(A14,Cadastro!$A$5:$A$304,0)),"")) | F14: =IF(A14="","",IFERROR(INDEX(Cadastro!$G$5:$G$304,MATCH(A14,Cadastro!$A$5:$A$304,0)),"")) | G14: =IF(A14="","",IFERROR(INDEX(Cadastro!$D$5:$D$304,MATCH(A14,Cadastro!$A$5:$A$304,0)),"")) | H14: =IF(A14="","",IFERROR(INDEX(Cadastro!$I$5:$I$304,MATCH(A14,Cadastro!$A$5:$A$304,0)),"")) | I14: =IF(OR(C14="",$E$4=""),"",C14/$E$4-1) | J14: =IF(I14="","",IF(AND(D14="S",I14>0,I14<=Parâmetros!$B$9),"S","N")) | K14: =IF(I14="",0,IF(OR(I14=0,J14="S"),1,0)) -> 0 | L14: =IF(K14=0,"",VALUE(RIGHT(H14,1))*1000-IF(E14="S",100,0)-IF(F14="S",10,0)-IF(G14="MEI",1,0)-IFERROR(INDEX(Cadastro!$W$5:$W$304,MATCH(A14,Cadastro!$A$5:$A$304,0))/100,0)+I14) | M14: =IF(L14="",0,IF(L14=MIN($L$11:$L$22),1,0)) -> 0 | N14: =IF(M14=0,"",IF(I14=0,"Menor preço",IF(VALUE(RIGHT(H14,1))<VALUE(RIGHT(INDEX($H$11:$H$22,MATCH(0,$I$11:$I$22,0)),1)),"Empate ficto + preferência local — deve cobrir o menor preço em 1 dia útil","Empate ficto — deve cobrir o menor preço em 1 dia útil")))
B15: =IF(A15="","",IFERROR(INDEX(Cadastro!$B$5:$B$304,MATCH(A15,Cadastro!$A$5:$A$304,0)),"ID não encontrado")) | D15: =IF(A15="","",IFERROR(INDEX(Cadastro!$E$5:$E$304,MATCH(A15,Cadastro!$A$5:$A$304,0)),"")) | E15: =IF(A15="","",IFERROR(INDEX(Cadastro!$F$5:$F$304,MATCH(A15,Cadastro!$A$5:$A$304,0)),"")) | F15: =IF(A15="","",IFERROR(INDEX(Cadastro!$G$5:$G$304,MATCH(A15,Cadastro!$A$5:$A$304,0)),"")) | G15: =IF(A15="","",IFERROR(INDEX(Cadastro!$D$5:$D$304,MATCH(A15,Cadastro!$A$5:$A$304,0)),"")) | H15: =IF(A15="","",IFERROR(INDEX(Cadastro!$I$5:$I$304,MATCH(A15,Cadastro!$A$5:$A$304,0)),"")) | I15: =IF(OR(C15="",$E$4=""),"",C15/$E$4-1) | J15: =IF(I15="","",IF(AND(D15="S",I15>0,I15<=Parâmetros!$B$9),"S","N")) | K15: =IF(I15="",0,IF(OR(I15=0,J15="S"),1,0)) -> 0 | L15: =IF(K15=0,"",VALUE(RIGHT(H15,1))*1000-IF(E15="S",100,0)-IF(F15="S",10,0)-IF(G15="MEI",1,0)-IFERROR(INDEX(Cadastro!$W$5:$W$304,MATCH(A15,Cadastro!$A$5:$A$304,0))/100,0)+I15) | M15: =IF(L15="",0,IF(L15=MIN($L$11:$L$22),1,0)) -> 0 | N15: =IF(M15=0,"",IF(I15=0,"Menor preço",IF(VALUE(RIGHT(H15,1))<VALUE(RIGHT(INDEX($H$11:$H$22,MATCH(0,$I$11:$I$22,0)),1)),"Empate ficto + preferência local — deve cobrir o menor preço em 1 dia útil","Empate ficto — deve cobrir o menor preço em 1 dia útil")))
B16: =IF(A16="","",IFERROR(INDEX(Cadastro!$B$5:$B$304,MATCH(A16,Cadastro!$A$5:$A$304,0)),"ID não encontrado")) | D16: =IF(A16="","",IFERROR(INDEX(Cadastro!$E$5:$E$304,MATCH(A16,Cadastro!$A$5:$A$304,0)),"")) | E16: =IF(A16="","",IFERROR(INDEX(Cadastro!$F$5:$F$304,MATCH(A16,Cadastro!$A$5:$A$304,0)),"")) | F16: =IF(A16="","",IFERROR(INDEX(Cadastro!$G$5:$G$304,MATCH(A16,Cadastro!$A$5:$A$304,0)),"")) | G16: =IF(A16="","",IFERROR(INDEX(Cadastro!$D$5:$D$304,MATCH(A16,Cadastro!$A$5:$A$304,0)),"")) | H16: =IF(A16="","",IFERROR(INDEX(Cadastro!$I$5:$I$304,MATCH(A16,Cadastro!$A$5:$A$304,0)),"")) | I16: =IF(OR(C16="",$E$4=""),"",C16/$E$4-1) | J16: =IF(I16="","",IF(AND(D16="S",I16>0,I16<=Parâmetros!$B$9),"S","N")) | K16: =IF(I16="",0,IF(OR(I16=0,J16="S"),1,0)) -> 0 | L16: =IF(K16=0,"",VALUE(RIGHT(H16,1))*1000-IF(E16="S",100,0)-IF(F16="S",10,0)-IF(G16="MEI",1,0)-IFERROR(INDEX(Cadastro!$W$5:$W$304,MATCH(A16,Cadastro!$A$5:$A$304,0))/100,0)+I16) | M16: =IF(L16="",0,IF(L16=MIN($L$11:$L$22),1,0)) -> 0 | N16: =IF(M16=0,"",IF(I16=0,"Menor preço",IF(VALUE(RIGHT(H16,1))<VALUE(RIGHT(INDEX($H$11:$H$22,MATCH(0,$I$11:$I$22,0)),1)),"Empate ficto + preferência local — deve cobrir o menor preço em 1 dia útil","Empate ficto — deve cobrir o menor preço em 1 dia útil")))
B17: =IF(A17="","",IFERROR(INDEX(Cadastro!$B$5:$B$304,MATCH(A17,Cadastro!$A$5:$A$304,0)),"ID não encontrado")) | D17: =IF(A17="","",IFERROR(INDEX(Cadastro!$E$5:$E$304,MATCH(A17,Cadastro!$A$5:$A$304,0)),"")) | E17: =IF(A17="","",IFERROR(INDEX(Cadastro!$F$5:$F$304,MATCH(A17,Cadastro!$A$5:$A$304,0)),"")) | F17: =IF(A17="","",IFERROR(INDEX(Cadastro!$G$5:$G$304,MATCH(A17,Cadastro!$A$5:$A$304,0)),"")) | G17: =IF(A17="","",IFERROR(INDEX(Cadastro!$D$5:$D$304,MATCH(A17,Cadastro!$A$5:$A$304,0)),"")) | H17: =IF(A17="","",IFERROR(INDEX(Cadastro!$I$5:$I$304,MATCH(A17,Cadastro!$A$5:$A$304,0)),"")) | I17: =IF(OR(C17="",$E$4=""),"",C17/$E$4-1) | J17: =IF(I17="","",IF(AND(D17="S",I17>0,I17<=Parâmetros!$B$9),"S","N")) | K17: =IF(I17="",0,IF(OR(I17=0,J17="S"),1,0)) -> 0 | L17: =IF(K17=0,"",VALUE(RIGHT(H17,1))*1000-IF(E17="S",100,0)-IF(F17="S",10,0)-IF(G17="MEI",1,0)-IFERROR(INDEX(Cadastro!$W$5:$W$304,MATCH(A17,Cadastro!$A$5:$A$304,0))/100,0)+I17) | M17: =IF(L17="",0,IF(L17=MIN($L$11:$L$22),1,0)) -> 0 | N17: =IF(M17=0,"",IF(I17=0,"Menor preço",IF(VALUE(RIGHT(H17,1))<VALUE(RIGHT(INDEX($H$11:$H$22,MATCH(0,$I$11:$I$22,0)),1)),"Empate ficto + preferência local — deve cobrir o menor preço em 1 dia útil","Empate ficto — deve cobrir o menor preço em 1 dia útil")))
B18: =IF(A18="","",IFERROR(INDEX(Cadastro!$B$5:$B$304,MATCH(A18,Cadastro!$A$5:$A$304,0)),"ID não encontrado")) | D18: =IF(A18="","",IFERROR(INDEX(Cadastro!$E$5:$E$304,MATCH(A18,Cadastro!$A$5:$A$304,0)),"")) | E18: =IF(A18="","",IFERROR(INDEX(Cadastro!$F$5:$F$304,MATCH(A18,Cadastro!$A$5:$A$304,0)),"")) | F18: =IF(A18="","",IFERROR(INDEX(Cadastro!$G$5:$G$304,MATCH(A18,Cadastro!$A$5:$A$304,0)),"")) | G18: =IF(A18="","",IFERROR(INDEX(Cadastro!$D$5:$D$304,MATCH(A18,Cadastro!$A$5:$A$304,0)),"")) | H18: =IF(A18="","",IFERROR(INDEX(Cadastro!$I$5:$I$304,MATCH(A18,Cadastro!$A$5:$A$304,0)),"")) | I18: =IF(OR(C18="",$E$4=""),"",C18/$E$4-1) | J18: =IF(I18="","",IF(AND(D18="S",I18>0,I18<=Parâmetros!$B$9),"S","N")) | K18: =IF(I18="",0,IF(OR(I18=0,J18="S"),1,0)) -> 0 | L18: =IF(K18=0,"",VALUE(RIGHT(H18,1))*1000-IF(E18="S",100,0)-IF(F18="S",10,0)-IF(G18="MEI",1,0)-IFERROR(INDEX(Cadastro!$W$5:$W$304,MATCH(A18,Cadastro!$A$5:$A$304,0))/100,0)+I18) | M18: =IF(L18="",0,IF(L18=MIN($L$11:$L$22),1,0)) -> 0 | N18: =IF(M18=0,"",IF(I18=0,"Menor preço",IF(VALUE(RIGHT(H18,1))<VALUE(RIGHT(INDEX($H$11:$H$22,MATCH(0,$I$11:$I$22,0)),1)),"Empate ficto + preferência local — deve cobrir o menor preço em 1 dia útil","Empate ficto — deve cobrir o menor preço em 1 dia útil")))
B19: =IF(A19="","",IFERROR(INDEX(Cadastro!$B$5:$B$304,MATCH(A19,Cadastro!$A$5:$A$304,0)),"ID não encontrado")) | D19: =IF(A19="","",IFERROR(INDEX(Cadastro!$E$5:$E$304,MATCH(A19,Cadastro!$A$5:$A$304,0)),"")) | E19: =IF(A19="","",IFERROR(INDEX(Cadastro!$F$5:$F$304,MATCH(A19,Cadastro!$A$5:$A$304,0)),"")) | F19: =IF(A19="","",IFERROR(INDEX(Cadastro!$G$5:$G$304,MATCH(A19,Cadastro!$A$5:$A$304,0)),"")) | G19: =IF(A19="","",IFERROR(INDEX(Cadastro!$D$5:$D$304,MATCH(A19,Cadastro!$A$5:$A$304,0)),"")) | H19: =IF(A19="","",IFERROR(INDEX(Cadastro!$I$5:$I$304,MATCH(A19,Cadastro!$A$5:$A$304,0)),"")) | I19: =IF(OR(C19="",$E$4=""),"",C19/$E$4-1) | J19: =IF(I19="","",IF(AND(D19="S",I19>0,I19<=Parâmetros!$B$9),"S","N")) | K19: =IF(I19="",0,IF(OR(I19=0,J19="S"),1,0)) -> 0 | L19: =IF(K19=0,"",VALUE(RIGHT(H19,1))*1000-IF(E19="S",100,0)-IF(F19="S",10,0)-IF(G19="MEI",1,0)-IFERROR(INDEX(Cadastro!$W$5:$W$304,MATCH(A19,Cadastro!$A$5:$A$304,0))/100,0)+I19) | M19: =IF(L19="",0,IF(L19=MIN($L$11:$L$22),1,0)) -> 0 | N19: =IF(M19=0,"",IF(I19=0,"Menor preço",IF(VALUE(RIGHT(H19,1))<VALUE(RIGHT(INDEX($H$11:$H$22,MATCH(0,$I$11:$I$22,0)),1)),"Empate ficto + preferência local — deve cobrir o menor preço em 1 dia útil","Empate ficto — deve cobrir o menor preço em 1 dia útil")))
B20: =IF(A20="","",IFERROR(INDEX(Cadastro!$B$5:$B$304,MATCH(A20,Cadastro!$A$5:$A$304,0)),"ID não encontrado")) | D20: =IF(A20="","",IFERROR(INDEX(Cadastro!$E$5:$E$304,MATCH(A20,Cadastro!$A$5:$A$304,0)),"")) | E20: =IF(A20="","",IFERROR(INDEX(Cadastro!$F$5:$F$304,MATCH(A20,Cadastro!$A$5:$A$304,0)),"")) | F20: =IF(A20="","",IFERROR(INDEX(Cadastro!$G$5:$G$304,MATCH(A20,Cadastro!$A$5:$A$304,0)),"")) | G20: =IF(A20="","",IFERROR(INDEX(Cadastro!$D$5:$D$304,MATCH(A20,Cadastro!$A$5:$A$304,0)),"")) | H20: =IF(A20="","",IFERROR(INDEX(Cadastro!$I$5:$I$304,MATCH(A20,Cadastro!$A$5:$A$304,0)),"")) | I20: =IF(OR(C20="",$E$4=""),"",C20/$E$4-1) | J20: =IF(I20="","",IF(AND(D20="S",I20>0,I20<=Parâmetros!$B$9),"S","N")) | K20: =IF(I20="",0,IF(OR(I20=0,J20="S"),1,0)) -> 0 | L20: =IF(K20=0,"",VALUE(RIGHT(H20,1))*1000-IF(E20="S",100,0)-IF(F20="S",10,0)-IF(G20="MEI",1,0)-IFERROR(INDEX(Cadastro!$W$5:$W$304,MATCH(A20,Cadastro!$A$5:$A$304,0))/100,0)+I20) | M20: =IF(L20="",0,IF(L20=MIN($L$11:$L$22),1,0)) -> 0 | N20: =IF(M20=0,"",IF(I20=0,"Menor preço",IF(VALUE(RIGHT(H20,1))<VALUE(RIGHT(INDEX($H$11:$H$22,MATCH(0,$I$11:$I$22,0)),1)),"Empate ficto + preferência local — deve cobrir o menor preço em 1 dia útil","Empate ficto — deve cobrir o menor preço em 1 dia útil")))
B21: =IF(A21="","",IFERROR(INDEX(Cadastro!$B$5:$B$304,MATCH(A21,Cadastro!$A$5:$A$304,0)),"ID não encontrado")) | D21: =IF(A21="","",IFERROR(INDEX(Cadastro!$E$5:$E$304,MATCH(A21,Cadastro!$A$5:$A$304,0)),"")) | E21: =IF(A21="","",IFERROR(INDEX(Cadastro!$F$5:$F$304,MATCH(A21,Cadastro!$A$5:$A$304,0)),"")) | F21: =IF(A21="","",IFERROR(INDEX(Cadastro!$G$5:$G$304,MATCH(A21,Cadastro!$A$5:$A$304,0)),"")) | G21: =IF(A21="","",IFERROR(INDEX(Cadastro!$D$5:$D$304,MATCH(A21,Cadastro!$A$5:$A$304,0)),"")) | H21: =IF(A21="","",IFERROR(INDEX(Cadastro!$I$5:$I$304,MATCH(A21,Cadastro!$A$5:$A$304,0)),"")) | I21: =IF(OR(C21="",$E$4=""),"",C21/$E$4-1) | J21: =IF(I21="","",IF(AND(D21="S",I21>0,I21<=Parâmetros!$B$9),"S","N")) | K21: =IF(I21="",0,IF(OR(I21=0,J21="S"),1,0)) -> 0 | L21: =IF(K21=0,"",VALUE(RIGHT(H21,1))*1000-IF(E21="S",100,0)-IF(F21="S",10,0)-IF(G21="MEI",1,0)-IFERROR(INDEX(Cadastro!$W$5:$W$304,MATCH(A21,Cadastro!$A$5:$A$304,0))/100,0)+I21) | M21: =IF(L21="",0,IF(L21=MIN($L$11:$L$22),1,0)) -> 0 | N21: =IF(M21=0,"",IF(I21=0,"Menor preço",IF(VALUE(RIGHT(H21,1))<VALUE(RIGHT(INDEX($H$11:$H$22,MATCH(0,$I$11:$I$22,0)),1)),"Empate ficto + preferência local — deve cobrir o menor preço em 1 dia útil","Empate ficto — deve cobrir o menor preço em 1 dia útil")))
B22: =IF(A22="","",IFERROR(INDEX(Cadastro!$B$5:$B$304,MATCH(A22,Cadastro!$A$5:$A$304,0)),"ID não encontrado")) | D22: =IF(A22="","",IFERROR(INDEX(Cadastro!$E$5:$E$304,MATCH(A22,Cadastro!$A$5:$A$304,0)),"")) | E22: =IF(A22="","",IFERROR(INDEX(Cadastro!$F$5:$F$304,MATCH(A22,Cadastro!$A$5:$A$304,0)),"")) | F22: =IF(A22="","",IFERROR(INDEX(Cadastro!$G$5:$G$304,MATCH(A22,Cadastro!$A$5:$A$304,0)),"")) | G22: =IF(A22="","",IFERROR(INDEX(Cadastro!$D$5:$D$304,MATCH(A22,Cadastro!$A$5:$A$304,0)),"")) | H22: =IF(A22="","",IFERROR(INDEX(Cadastro!$I$5:$I$304,MATCH(A22,Cadastro!$A$5:$A$304,0)),"")) | I22: =IF(OR(C22="",$E$4=""),"",C22/$E$4-1) | J22: =IF(I22="","",IF(AND(D22="S",I22>0,I22<=Parâmetros!$B$9),"S","N")) | K22: =IF(I22="",0,IF(OR(I22=0,J22="S"),1,0)) -> 0 | L22: =IF(K22=0,"",VALUE(RIGHT(H22,1))*1000-IF(E22="S",100,0)-IF(F22="S",10,0)-IF(G22="MEI",1,0)-IFERROR(INDEX(Cadastro!$W$5:$W$304,MATCH(A22,Cadastro!$A$5:$A$304,0))/100,0)+I22) | M22: =IF(L22="",0,IF(L22=MIN($L$11:$L$22),1,0)) -> 0 | N22: =IF(M22=0,"",IF(I22=0,"Menor preço",IF(VALUE(RIGHT(H22,1))<VALUE(RIGHT(INDEX($H$11:$H$22,MATCH(0,$I$11:$I$22,0)),1)),"Empate ficto + preferência local — deve cobrir o menor preço em 1 dia útil","Empate ficto — deve cobrir o menor preço em 1 dia útil")))
A24: Como ler
A25: 1) "Empate ficto = S": pequeno negócio até 10% acima do menor preço. 2) Entre o menor preço e os empatados fictos, a pontuação prioriza o território mais próximo (T1 < T2 < T3), depois mulher, mulher negra/CadÚnico, MEI e avaliação. 3) Se o vencedor sugerido não é o de menor preço, ele deve apresentar proposta igual ou inferior ao menor preço em 1 dia útil (item 8.2 do Edital); se não cobrir, o próximo da pontuação é convocado. 4) Persistindo empate exato, faça sorteio e registre em ata.

Sheet Banco de Preços
A1: Banco de Preços
A2: Registre cada preço praticado ou cotado. A tabela à direita calcula a média por item e o teto para o rodízio (média + margem).
A4: Data | B4: Linha | C4: Item (descrição padronizada) | D4: Unidade | E4: Preço unitário (R$) | F4: Fonte (contratação / cotação / Painel de Preços / pesquisa) | G4: Fornecedor / referência | H4: Observações | J4: Consulta de referência
A5: 46315 | B5: L01 | C5: Kit lanche (suco 200 ml + sanduíche + fruta) | D5: unid. | E5: 19.25 | F5: Contratação 2026-BM-001 | G5: F001 | H5: EXEMPLO — apagar | J5: Item (copie a descrição padronizada) | K5: Kit lanche (suco 200 ml + sanduíche + fruta)
A6: 46275 | B6: L01 | C6: Kit lanche (suco 200 ml + sanduíche + fruta) | D6: unid. | E6: 21 | F6: Cotação | G6: F006 | H6: EXEMPLO — apagar | J6: Nº de registros | K6: =COUNTIF(C5:C504,K5) -> 2
A7: 46318 | B7: L03 | C7: Sonorização + iluminação palco 6x4, 6h | D7: diária | E7: 17200 | F7: Contratação 2026-BM-002 | G7: F002 | H7: EXEMPLO — apagar | J7: Preço médio (R$) | K7: =IFERROR(AVERAGEIF(C5:C504,K5,E5:E504),"") -> 20.125
A8: 46331 | B8: L07 | C8: Oficina de dança sênior (2h) | D8: hora-aula | E8: 250 | F8: Contratação 2026-JL-004 | G8: F004 | H8: EXEMPLO — apagar | J8: Menor preço (R$) | K8: =IFERROR(_xlfn.MINIFS(E5:E504,C5:C504,K5),"") -> 19.25
J9: Teto para o rodízio (média + margem) | K9: =IF(K7="","",K7*(1+Parâmetros!$B$11)) -> 22.1375

Sheet Sanções
A1: Registro de processos sancionadores
A2: Um processo por linha. Prazos conforme art. 26 da Política.
A4: Nº processo | B4: ID fornecedor | C4: Fornecedor | D4: Dossiê relacionado | E4: Infração (Anexo XII) | F4: Data da notificação | G4: Prazo da defesa (5 d.u.) | H4: Defesa recebida? | I4: Decisão da Comissão | J4: Data da decisão | K4: Recurso? | L4: Decisão da Diretoria | M4: Sanção aplicada | N4: Início | O4: Fim | P4: Observações
A5: PS-2026-001 | B5: F005 | C5: =IF(B5="","",IFERROR(INDEX(Cadastro!$B$5:$B$304,MATCH(B5,Cadastro!$A$5:$A$304,0)),"ID não encontrado")) -> Gráfica Baixada EPP | D5: 2026-JL-005 | E5: Atraso injustificado na entrega | F5: 46351 | G5: =IF(F5="","",WORKDAY(F5,5)) -> 46358 | H5: S | I5: Advertência | J5: 46365 | K5: N | M5: Advertência | P5: EXEMPLO — apagar
C6: =IF(B6="","",IFERROR(INDEX(Cadastro!$B$5:$B$304,MATCH(B6,Cadastro!$A$5:$A$304,0)),"ID não encontrado")) | G6: =IF(F6="","",WORKDAY(F6,5))
C7: =IF(B7="","",IFERROR(INDEX(Cadastro!$B$5:$B$304,MATCH(B7,Cadastro!$A$5:$A$304,0)),"ID não encontrado")) | G7: =IF(F7="","",WORKDAY(F7,5))
C8: =IF(B8="","",IFERROR(INDEX(Cadastro!$B$5:$B$304,MATCH(B8,Cadastro!$A$5:$A$304,0)),"ID não encontrado")) | G8: =IF(F8="","",WORKDAY(F8,5))
C9: =IF(B9="","",IFERROR(INDEX(Cadastro!$B$5:$B$304,MATCH(B9,Cadastro!$A$5:$A$304,0)),"ID não encontrado")) | G9: =IF(F9="","",WORKDAY(F9,5))
C10: =IF(B10="","",IFERROR(INDEX(Cadastro!$B$5:$B$304,MATCH(B10,Cadastro!$A$5:$A$304,0)),"ID não encontrado")) | G10: =IF(F10="","",WORKDAY(F10,5))
C11: =IF(B11="","",IFERROR(INDEX(Cadastro!$B$5:$B$304,MATCH(B11,Cadastro!$A$5:$A$304,0)),"ID não encontrado")) | G11: =IF(F11="","",WORKDAY(F11,5))
C12: =IF(B12="","",IFERROR(INDEX(Cadastro!$B$5:$B$304,MATCH(B12,Cadastro!$A$5:$A$304,0)),"ID não encontrado")) | G12: =IF(F12="","",WORKDAY(F12,5))
C13: =IF(B13="","",IFERROR(INDEX(Cadastro!$B$5:$B$304,MATCH(B13,Cadastro!$A$5:$A$304,0)),"ID não encontrado")) | G13: =IF(F13="","",WORKDAY(F13,5))
C14: =IF(B14="","",IFERROR(INDEX(Cadastro!$B$5:$B$304,MATCH(B14,Cadastro!$A$5:$A$304,0)),"ID não encontrado")) | G14: =IF(F14="","",WORKDAY(F14,5))
C15: =IF(B15="","",IFERROR(INDEX(Cadastro!$B$5:$B$304,MATCH(B15,Cadastro!$A$5:$A$304,0)),"ID não encontrado")) | G15: =IF(F15="","",WORKDAY(F15,5))
C16: =IF(B16="","",IFERROR(INDEX(Cadastro!$B$5:$B$304,MATCH(B16,Cadastro!$A$5:$A$304,0)),"ID não encontrado")) | G16: =IF(F16="","",WORKDAY(F16,5))
C17: =IF(B17="","",IFERROR(INDEX(Cadastro!$B$5:$B$304,MATCH(B17,Cadastro!$A$5:$A$304,0)),"ID não encontrado")) | G17: =IF(F17="","",WORKDAY(F17,5))
... C104: =IF(B104="","",IFERROR(INDEX(Cadastro!$B$5:$B$304,MATCH(B104,Cadastro!$A$5:$A$304,0)),"ID não encontrado")) | G104: =IF(F104="","",WORKDAY(F104,5))

Sheet Indicadores
A1: Indicadores do Contrata + NATA — relatório semestral
A2: Calculados automaticamente a partir das abas Cadastro e Contratações. Filtre o período nas células amarelas.
A4: Período — início | B4: 46204
A5: Período — fim | B5: 46387
A7: Indicador | B7: Valor | C7: Meta | D7: Situação | E7: Cálculo
A8: Credenciados ativos | B8: =COUNTIF(Cadastro!$O$5:$O$304,"Ativo") -> 5 | E8: Cadastro, status = Ativo
A9: dos quais pequenos negócios | B9: =COUNTIFS(Cadastro!$O$5:$O$304,"Ativo",Cadastro!$E$5:$E$304,"S") -> 5 | E9: Porte MEI/ME/EPP/Coop./PF
A10: dos quais liderados por mulheres | B10: =COUNTIFS(Cadastro!$O$5:$O$304,"Ativo",Cadastro!$F$5:$F$304,"S") -> 3 | E10: Anexo IV
A11: dos quais do território T1 | B11: =COUNTIFS(Cadastro!$O$5:$O$304,"Ativo",Cadastro!$I$5:$I$304,"T1") -> 3 | E11: Sede em Mesquita/município do projeto
A12: Credenciados com certidões a renovar | B12: =COUNTIF(Cadastro!$T$5:$T$304,"RENOVAR") -> 0 | E12: Alerta da aba Cadastro
A13: Contratações no período (nº) | B13: =COUNTIFS(Contratações!$O$5:$O$504,">="&$B$4,Contratações!$O$5:$O$504,"<="&$B$5) -> 5 | E13: Data da OF/OS dentro do período
A14: Valor contratado no período (R$) | B14: =SUMIFS(Contratações!$N$5:$N$504,Contratações!$O$5:$O$504,">="&$B$4,Contratações!$O$5:$O$504,"<="&$B$5) -> 40550 | E14: Soma do valor contratado
A15: % do valor com pequenos negócios | B15: =IFERROR(SUMIFS(Contratações!$N$5:$N$504,Contratações!$O$5:$O$504,">="&$B$4,Contratações!$O$5:$O$504,"<="&$B$5,Contratações!$K$5:$K$504,"S")/B14,0) -> 1 | C15: =Parâmetros!$B$14 -> 0.7 | D15: =IF(B15>=C15,"OK","ATENÇÃO") -> OK | E15: Art. 15 da Política
A16: % do valor com negócios liderados por mulheres | B16: =IFERROR(SUMIFS(Contratações!$N$5:$N$504,Contratações!$O$5:$O$504,">="&$B$4,Contratações!$O$5:$O$504,"<="&$B$5,Contratações!$L$5:$L$504,"S")/B14,0) -> 0.43033292 | C16: =Parâmetros!$B$15 -> 0.3 | D16: =IF(B16>=C16,"OK","ATENÇÃO") -> OK | E16: Art. 15 da Política
A17: % do valor com fornecedores T1 | B17: =IFERROR(SUMIFS(Contratações!$N$5:$N$504,Contratações!$O$5:$O$504,">="&$B$4,Contratações!$O$5:$O$504,"<="&$B$5,Contratações!$M$5:$M$504,"T1")/B14,0) -> 0.43033292 | C17: =Parâmetros!$B$16 -> 0.5 | D17: =IF(B17>=C17,"OK","ATENÇÃO") -> ATENÇÃO | E17: Art. 15 da Política
A18: Contratações Faixa 1 (nº) | B18: =COUNTIFS(Contratações!$O$5:$O$504,">="&$B$4,Contratações!$O$5:$O$504,"<="&$B$5,Contratações!$G$5:$G$504,"Faixa 1") -> 4
A19: Contratações Faixa 2 (nº) | B19: =COUNTIFS(Contratações!$O$5:$O$504,">="&$B$4,Contratações!$O$5:$O$504,"<="&$B$5,Contratações!$G$5:$G$504,"Faixa 2") -> 1
A20: Contratações Faixa 3 (nº) | B20: =COUNTIFS(Contratações!$O$5:$O$504,">="&$B$4,Contratações!$O$5:$O$504,"<="&$B$5,Contratações!$G$5:$G$504,"Faixa 3") -> 0
A21: Tempo médio DFD → OF (dias úteis) | B21: =IFERROR(AVERAGEIFS(Contratações!$P$5:$P$504,Contratações!$O$5:$O$504,">="&$B$4,Contratações!$O$5:$O$504,"<="&$B$5),0) -> 2.8 | C21: 4 | D21: =IF(B21<=C21,"OK","ATENÇÃO") -> OK | E21: Manual, item 7
A22: Avaliação média dos fornecedores | B22: =IFERROR(AVERAGEIFS(Contratações!$R$5:$R$504,Contratações!$O$5:$O$504,">="&$B$4,Contratações!$O$5:$O$504,"<="&$B$5,Contratações!$R$5:$R$504,">0"),0) -> 4.4 | C22: =Parâmetros!$B$17 -> 4 | D22: =IF(B22>=C22,"OK","ATENÇÃO") -> OK | E22: Termos de Recebimento
A23: % de contratações de urgência | B23: =IFERROR(COUNTIFS(Contratações!$O$5:$O$504,">="&$B$4,Contratações!$O$5:$O$504,"<="&$B$5,Contratações!$T$5:$T$504,"S")/B13,0) -> 0.2 | C23: =Parâmetros!$B$18 -> 0.05 | D23: =IF(B23<=C23,"OK","ATENÇÃO") -> ATENÇÃO | E23: Meta é um máximo
A24: % de dossiês completos | B24: =IFERROR(COUNTIFS(Contratações!$O$5:$O$504,">="&$B$4,Contratações!$O$5:$O$504,"<="&$B$5,Contratações!$W$5:$W$504,"S")/B13,0) -> 0.8 | C24: 1 | D24: =IF(B24>=C24,"OK","ATENÇÃO") -> ATENÇÃO | E24: Checklist Anexo XIII
A25: Processos sancionadores abertos no período | B25: =COUNTIFS(Sanções!$F$5:$F$104,">="&$B$4,Sanções!$F$5:$F$104,"<="&$B$5) -> 1 | E25: Aba Sanções
A29: Contratações por linha de fornecimento (período)
A30: Linha | B30: Nome | C30: Nº contratações | D30: Valor (R$) | E30: Credenciados ativos
A31: =Parâmetros!H24 -> L01 | B31: =Parâmetros!I24 -> Alimentação — lanches e kits | C31: =COUNTIFS(Contratações!$O$5:$O$504,">="&$B$4,Contratações!$O$5:$O$504,"<="&$B$5,Contratações!$D$5:$D$504,A31) -> 1 | D31: =SUMIFS(Contratações!$N$5:$N$504,Contratações!$O$5:$O$504,">="&$B$4,Contratações!$O$5:$O$504,"<="&$B$5,Contratações!$D$5:$D$504,A31) -> 3850 | E31: =SUMPRODUCT((Cadastro!$O$5:$O$304="Ativo")*ISNUMBER(SEARCH(A31,Cadastro!$J$5:$J$304))) -> 1
A32: =Parâmetros!H25 -> L02 | B32: =Parâmetros!I25 -> Bufê e churrasqueiro | C32: =COUNTIFS(Contratações!$O$5:$O$504,">="&$B$4,Contratações!$O$5:$O$504,"<="&$B$5,Contratações!$D$5:$D$504,A32) -> 0 | D32: =SUMIFS(Contratações!$N$5:$N$504,Contratações!$O$5:$O$504,">="&$B$4,Contratações!$O$5:$O$504,"<="&$B$5,Contratações!$D$5:$D$504,A32) -> 0 | E32: =SUMPRODUCT((Cadastro!$O$5:$O$304="Ativo")*ISNUMBER(SEARCH(A32,Cadastro!$J$5:$J$304))) -> 1
A33: =Parâmetros!H26 -> L03 | B33: =Parâmetros!I26 -> Sonorização e música | C33: =COUNTIFS(Contratações!$O$5:$O$504,">="&$B$4,Contratações!$O$5:$O$504,"<="&$B$5,Contratações!$D$5:$D$504,A33) -> 1 | D33: =SUMIFS(Contratações!$N$5:$N$504,Contratações!$O$5:$O$504,">="&$B$4,Contratações!$O$5:$O$504,"<="&$B$5,Contratações!$D$5:$D$504,A33) -> 17200 | E33: =SUMPRODUCT((Cadastro!$O$5:$O$304="Ativo")*ISNUMBER(SEARCH(A33,Cadastro!$J$5:$J$304))) -> 1
A34: =Parâmetros!H27 -> L04 | B34: =Parâmetros!I27 -> Estruturas para eventos | C34: =COUNTIFS(Contratações!$O$5:$O$504,">="&$B$4,Contratações!$O$5:$O$504,"<="&$B$5,Contratações!$D$5:$D$504,A34) -> 0 | D34: =SUMIFS(Contratações!$N$5:$N$504,Contratações!$O$5:$O$504,">="&$B$4,Contratações!$O$5:$O$504,"<="&$B$5,Contratações!$D$5:$D$504,A34) -> 0 | E34: =SUMPRODUCT((Cadastro!$O$5:$O$304="Ativo")*ISNUMBER(SEARCH(A34,Cadastro!$J$5:$J$304))) -> 1
A35: =Parâmetros!H28 -> L05 | B35: =Parâmetros!I28 -> Locação de mobiliário e equipamentos | C35: =COUNTIFS(Contratações!$O$5:$O$504,">="&$B$4,Contratações!$O$5:$O$504,"<="&$B$5,Contratações!$D$5:$D$504,A35) -> 0 | D35: =SUMIFS(Contratações!$N$5:$N$504,Contratações!$O$5:$O$504,">="&$B$4,Contratações!$O$5:$O$504,"<="&$B$5,Contratações!$D$5:$D$504,A35) -> 0 | E35: =SUMPRODUCT((Cadastro!$O$5:$O$304="Ativo")*ISNUMBER(SEARCH(A35,Cadastro!$J$5:$J$304))) -> 0
A36: =Parâmetros!H29 -> L06 | B36: =Parâmetros!I29 -> Cerimonial e apoio a eventos | C36: =COUNTIFS(Contratações!$O$5:$O$504,">="&$B$4,Contratações!$O$5:$O$504,"<="&$B$5,Contratações!$D$5:$D$504,A36) -> 0 | D36: =SUMIFS(Contratações!$N$5:$N$504,Contratações!$O$5:$O$504,">="&$B$4,Contratações!$O$5:$O$504,"<="&$B$5,Contratações!$D$5:$D$504,A36) -> 0 | E36: =SUMPRODUCT((Cadastro!$O$5:$O$304="Ativo")*ISNUMBER(SEARCH(A36,Cadastro!$J$5:$J$304))) -> 0
A37: =Parâmetros!H30 -> L07 | B37: =Parâmetros!I30 -> Recreação, oficinas e atrações | C37: =COUNTIFS(Contratações!$O$5:$O$504,">="&$B$4,Contratações!$O$5:$O$504,"<="&$B$5,Contratações!$D$5:$D$504,A37) -> 1 | D37: =SUMIFS(Contratações!$N$5:$N$504,Contratações!$O$5:$O$504,">="&$B$4,Contratações!$O$5:$O$504,"<="&$B$5,Contratações!$D$5:$D$504,A37) -> 4000 | E37: =SUMPRODUCT((Cadastro!$O$5:$O$304="Ativo")*ISNUMBER(SEARCH(A37,Cadastro!$J$5:$J$304))) -> 1
A38: =Parâmetros!H31 -> L08 | B38: =Parâmetros!I31 -> Atividade física e bem-estar | C38: =COUNTIFS(Contratações!$O$5:$O$504,">="&$B$4,Contratações!$O$5:$O$504,"<="&$B$5,Contratações!$D$5:$D$504,A38) -> 0 | D38: =SUMIFS(Contratações!$N$5:$N$504,Contratações!$O$5:$O$504,">="&$B$4,Contratações!$O$5:$O$504,"<="&$B$5,Contratações!$D$5:$D$504,A38) -> 0 | E38: =SUMPRODUCT((Cadastro!$O$5:$O$304="Ativo")*ISNUMBER(SEARCH(A38,Cadastro!$J$5:$J$304))) -> 1
A39: =Parâmetros!H32 -> L09 | B39: =Parâmetros!I32 -> Fotografia e audiovisual | C39: =COUNTIFS(Contratações!$O$5:$O$504,">="&$B$4,Contratações!$O$5:$O$504,"<="&$B$5,Contratações!$D$5:$D$504,A39) -> 0 | D39: =SUMIFS(Contratações!$N$5:$N$504,Contratações!$O$5:$O$504,">="&$B$4,Contratações!$O$5:$O$504,"<="&$B$5,Contratações!$D$5:$D$504,A39) -> 0 | E39: =SUMPRODUCT((Cadastro!$O$5:$O$304="Ativo")*ISNUMBER(SEARCH(A39,Cadastro!$J$5:$J$304))) -> 0
A40: =Parâmetros!H33 -> L10 | B40: =Parâmetros!I33 -> Comunicação visual e impressão | C40: =COUNTIFS(Contratações!$O$5:$O$504,">="&$B$4,Contratações!$O$5:$O$504,"<="&$B$5,Contratações!$D$5:$D$504,A40) -> 1 | D40: =SUMIFS(Contratações!$N$5:$N$504,Contratações!$O$5:$O$504,">="&$B$4,Contratações!$O$5:$O$504,"<="&$B$5,Contratações!$D$5:$D$504,A40) -> 5900 | E40: =SUMPRODUCT((Cadastro!$O$5:$O$304="Ativo")*ISNUMBER(SEARCH(A40,Cadastro!$J$5:$J$304))) -> 1
A41: =Parâmetros!H34 -> L11 | B41: =Parâmetros!I34 -> Confecção e uniformes | C41: =COUNTIFS(Contratações!$O$5:$O$504,">="&$B$4,Contratações!$O$5:$O$504,"<="&$B$5,Contratações!$D$5:$D$504,A41) -> 0 | D41: =SUMIFS(Contratações!$N$5:$N$504,Contratações!$O$5:$O$504,">="&$B$4,Contratações!$O$5:$O$504,"<="&$B$5,Contratações!$D$5:$D$504,A41) -> 0 | E41: =SUMPRODUCT((Cadastro!$O$5:$O$304="Ativo")*ISNUMBER(SEARCH(A41,Cadastro!$J$5:$J$304))) -> 1
A42: =Parâmetros!H35 -> L12 | B42: =Parâmetros!I35 -> Artesanato e economia criativa | C42: =COUNTIFS(Contratações!$O$5:$O$504,">="&$B$4,Contratações!$O$5:$O$504,"<="&$B$5,Contratações!$D$5:$D$504,A42) -> 1 | D42: =SUMIFS(Contratações!$N$5:$N$504,Contratações!$O$5:$O$504,">="&$B$4,Contratações!$O$5:$O$504,"<="&$B$5,Contratações!$D$5:$D$504,A42) -> 9600 | E42: =SUMPRODUCT((Cadastro!$O$5:$O$304="Ativo")*ISNUMBER(SEARCH(A42,Cadastro!$J$5:$J$304))) -> 1
... A50: =Parâmetros!H43 -> L20 | B50: =Parâmetros!I43 -> Beleza e caracterização | C50: =COUNTIFS(Contratações!$O$5:$O$504,">="&$B$4,Contratações!$O$5:$O$504,"<="&$B$5,Contratações!$D$5:$D$504,A50) -> 0 | D50: =SUMIFS(Contratações!$N$5:$N$504,Contratações!$O$5:$O$504,">="&$B$4,Contratações!$O$5:$O$504,"<="&$B$5,Contratações!$D$5:$D$504,A50) -> 0 | E50: =SUMPRODUCT((Cadastro!$O$5:$O$304="Ativo")*ISNUMBER(SEARCH(A50,Cadastro!$J$5:$J$304))) -> 0
